Workbook
Name Comprar: [1]Param!#REF!
Name início_da_tarefa: [2]CronogramaDeProjeto!$E1
Name Início_do_projeto: '[4]Gráfico de Gantt'!$G$5
Name Início_do_projeto: '[3]Gráfico de Gantt'!$G$5
Name Início_do_projeto: '[3]Gráfico de Gantt'!$G$5
Name Início_do_projeto: '[4]Gráfico de Gantt'!$G$5
Name Início_do_projeto: '[3]Gráfico de Gantt'!$G$5
Name Início_do_projeto: '[4]Gráfico de Gantt'!$G$5
Name Início_do_projeto: '[3]Gráfico de Gantt'!$G$5
Name Início_do_projeto: '[5]Gráfico de Gantt'!$G$5
Name Início_do_projeto: 'Gráfico de Gantt'!$G$5
Name Periodicidade: [6]Param!$AB$5:$AB$9
Name progresso_da_tarefa: [2]CronogramaDeProjeto!$D1
Name Semana_de_exibição: '[4]Gráfico de Gantt'!$G$6
Name Semana_de_exibição: '[3]Gráfico de Gantt'!$G$6
Name Semana_de_exibição: '[3]Gráfico de Gantt'!$G$6
Name Semana_de_exibição: '[4]Gráfico de Gantt'!$G$6
Name Semana_de_exibição: '[3]Gráfico de Gantt'!$G$6
Name Semana_de_exibição: '[4]Gráfico de Gantt'!$G$6
Name Semana_de_exibição: '[3]Gráfico de Gantt'!$G$6
Name Semana_de_exibição: '[5]Gráfico de Gantt'!$G$6
Name Semana_de_exibição: 'Gráfico de Gantt'!$G$6
Name Status: [1]Param!#REF!
Name término_da_tarefa: [2]CronogramaDeProjeto!$F1
Name VersaoExcel: [6]Param!$D$15:$E$15
Name VersaoSR: [6]Param!$C$24:$C$26

Sheet Project Charter

Sheet WBS-MACRO-ATIVIDADE

Sheet WBS_Detalhado (ordem etapas)
B7: 4.1 Plano de ação detalhado da WBS (com dependência, tempo e recurso)
B9: Ref | C9: Etapas – Atividades - | D9: Dependência | E9: Data Início | F9: Data Fim | G9: Duração em dias corridos | H9: Conclusão | I9: Responsável | J9: Recursos | K9: Custos | L9: Obs | O9: Rede de Precedência de Atividades
B10: 1 | C10: Iniciação | K10: 2500 | P10: Atividades | Q10: Dependência | R10: Duração em dias
B11: 1.1 | C11: Definir os objetivos do dashboard e sua proposta de valor para análise de campanhas, clientes e pedidos Cannoli+FECAP | D11: 1.0 | E11: 45876 | F11: 45879 | G11: 4 | H11: 2ª | I11: GERENTE DE PROJETO | J11: Pessoas | K11: 2500 | O11: 1 | P11: Definir objetivos do dashboard | Q11: NÃO | R11: 4
B12: 1.2 | C12: Identificar as principais funcionalidades e recursos a serem incluídos no dashboard (análises de campanhas, clientes, pedidos) | D12: 1.1 | E12: 45878 | F12: 45881 | G12: 4 | H12: 2ª | I12: GERENTE DE PROJETO | J12: Pessoas | K12: 2000 | O12: 2 | P12: Identificar funcionalidades principais | Q12: 1 | R12: 4
B13: 1.3 | C13: Formar uma equipe de desenvolvimento e design para o projeto do dashboard | D13: 1.2 | E13: 45879 | F13: 45882 | G13: 4 | H13: 2ª | I13: GERENTE DE PROJETO | J13: Pessoas | K13: 3200 | O13: 3 | P13: Formar equipe de desenvolvimento e design | Q13: 2 | R13: 4
B14: 2 | C14: Planejamento | D14: 1.3 | K14: =SUM(K11:K13) -> 7700 | O14: 4 | P14: Análise de mercado | Q14: 2 | R14: 4
B15: 2.1 | C15: Análise de mercado (concorrentes e demandas) | D15: 2.1 | E15: 45879 | F15: 45882 | G15: 4 | H15: 2ª | I15: GERENTE DE PROJETO | J15: Pessoas | K15: 2000 | O15: 5 | P15: Definir requisitos detalhados (escopo) | Q15: 2 | R15: 4
B16: 2.2 | C16: Definir requisitos detalhados (escopo) | D16: 1.2 | E16: 45880 | F16: 45883 | G16: 4 | H16: 2ª | I16: GERENTE DE PROJETO | J16: Pessoas | K16: 2500 | O16: 6 | P16: Requisitos - Campanhas | Q16: 4, 5 | R16: 3
B17: 2.2.1 | C17: Requisitos – Análise de Campanhas (winback, loyalty, etc.) | D17: 2.2 | E17: 45880 | F17: 45883 | G17: 4 | H17: 2ª | I17: GERENTE DE PROJETO | J17: Pessoas | K17: 2500 | O17: 7 | P17: Requisitos - Clientes | Q17: 4, 5 | R17: 2
B18: 2.2.2 | C18: Requisitos – Análise de Clientes (perfil, status, etc.) | D18: 2.2 | E18: 45880 | F18: 45881 | G18: 2 | H18: 1ª | I18: GERENTE DE PROJETO | J18: Pessoas | K18: 2500 | O18: 8 | P18: Requisitos - Pedidos | Q18: 5 | R18: 2
B19: 2.2.3 | C19: Requisitos – Pedidos (delivery, indoor, takeout) | D19: 2.2 | E19: 45880 | F19: 45881 | G19: 2 | H19: 1ª | I19: GERENTE DE PROJETO | J19: Pessoas | K19: 2500 | O19: 9 | P19: Requisitos - Integração | Q19: 6 | R19: 3
B20: 2.2.4 | C20: Requisitos – Integração com fontes (Campaign, Customer, Order) | D20: 2.2 | E20: 45882 | F20: 45884 | G20: 3 | H20: 2ª | I20: GERENTE DE PROJETO | J20: Pessoas | K20: 2500 | O20: 10 | P20: Criar cronograma detalhado | Q20: 7, 8, 9 | R20: 2
B21: 2.2.5 | C21: Criar cronograma detalhado com marcos e prazos | D21: 2.2 | E21: 45883 | F21: 45884 | G21: 2 | H21: 1ª | I21: GERENTE DE PROJETO | J21: Pessoas | K21: 2500 | O21: 11 | P21: Design da interface (UI) | Q21: 3 | R21: 7
B22: 3 | C22: Design e Prototipagem | D22: 2.2.5 | K22: =SUM(K15:K21) -> 17000 | O22: 12 | P22: Experiência do usuário (UX) | Q22: 11 | R22: 7
B23: 3.1 | C23: Design da interface (UI) | D23: 1.3 | E23: 45880 | F23: 45893 | G23: 14 | H23: 1ª | I23: DESIGN | J23: Pessoas | K23: 2000 | O23: 13 | P23: Protótipos e testes de UI/UX | Q23: 12 | R23: 4
B24: 3.1.1 | C24: Definir navegação simples e intuitiva | D24: 3.1 | E24: 45880 | F24: 45886 | G24: 7 | H24: 1ª | I24: DESIGN | J24: Pessoas | K24: 2250 | O24: 14 | P24: Estrutura do dashboard (Front/Back-end) | Q24: 10, 13 | R24: 10
B25: 3.1.2 | C25: Criar protótipos interativos | D25: 3.1.1 | E25: 45882 | F25: 45889 | G25: 8 | H25: 1ª | I25: DESIGN | J25: Pessoas | K25: 2200 | O25: 15 | P25: Implementar funcionalidades (Campanhas/Clientes/Pedidos) | Q25: 14 | R25: 10
B26: 3.2 | C26: Design da experiência (UX) | D26: 3.1.2 | E26: 45883 | F26: 45891 | G26: 9 | H26: 1ª | I26: DESIGN | J26: Pessoas | K26: 2250 | O26: 16 | P26: Integração com sistemas (CampaignQueue, Customer, Order) | Q26: 15 | R26: 3
B27: 3.2.1 | C27: Propor interface limpa e intuitiva | D27: 3.2 | E27: 45884 | F27: 45892 | G27: 9 | H27: 2ª | I27: DESIGN | J27: Pessoas | K27: 2250 | O27: 17 | P27: Segurança e privacidade de dados | Q27: 16 | R27: 3
B28: 3.2.2 | C28: Teste de UI/UX com usuários | D28: 3.2 | E28: 45885 | F28: 45893 | G28: 9 | H28: 2ª | I28: DESIGN | J28: Pessoas | K28: 2250 | O28: 18 | P28: Testes de qualidade e usabilidade | Q28: 17 | R28: 4
B29: 4 | C29: Desenvolvimento | D29: 3.2.2 | K29: =SUM(K23:K28) -> 13200 | O29: 19 | P29: Correções de bugs e interface | Q29: 18 | R29: 3
B30: 4.1 | C30: Desenvolver estrutura do dashboard | D30: 4.1 | E30: 45883 | F30: 45892 | G30: 10 | H30: 2ª | I30: DESENVOLVIMENTO | J30: Pessoas | K30: 6000 | O30: 20 | P30: Lançamento (infraestrutura + treinamento) | Q30: 19 | R30: 6
B31: 4.1.2 | C31: Desenvolvimento Front-end (UI e interações) | D31: 4.1 | E31: 45888 | F31: 45897 | G31: 10 | H31: 1ª | I31: DESENVOLVIMENTO | J31: Pessoas | K31: 4000 | O31: 21 | P31: Pós-lançamento (monitoramento e suporte) | Q31: 20 | R31: 6
B32: 4.1.3 | C32: Codificação Back-end (processamento e dados) | D32: 4.1 | E32: 45898 | F32: 45900 | G32: 3 | H32: 2ª | I32: DESENVOLVIMENTO | J32: Pessoas | K32: 4500 | O32: 22 | P32: Avaliação, melhorias contínuas e expansão | Q32: 21 | R32: 6
B33: 4.2 | C33: Implementar funcionalidades principais | D33: 2.2 | E33: 45890 | F33: 45892 | G33: 3 | H33: 1ª | I33: DESENVOLVIMENTO | J33: Pessoas | K33: 4000
B34: 4.2.1 | C34: Módulo de Campanhas | D34: 4.2 | E34: 45892 | F34: 45899 | G34: 8 | H34: 2ª | I34: DESENVOLVIMENTO | J34: Pessoas | K34: 4000
B35: 4.2.2 | C35: Módulo de Clientes | D35: 4.2 | E35: 45892 | F35: 45900 | G35: 9 | H35: 1ª | I35: DESENVOLVIMENTO | J35: Pessoas | K35: 4000
B36: 4.2.3 | C36: Módulo de Pedidos e Canais de Venda | D36: 4.2 | E36: 45892 | F36: 45902 | G36: 11 | H36: 2ª | I36: DESENVOLVIMENTO | J36: Pessoas | K36: 5500
B37: 5 | C37: Integração com sistemas de monitoramento de saúde | D37: 4.2 | K37: =SUM(K30:K36) -> 32000
B38: 5.1 | C38: Integrar CampaignQueue, Campaign, Customer, Order | D38: 4.2 | E38: 45892 | F38: 45894 | G38: 3 | H38: 2ª | I38: SEGURANÇA | J38: Pessoas | K38: 3000
B39: 5.2 | C39: Garantir segurança e privacidade dos dados | D39: 5.1 | E39: 45892 | F39: 45894 | G39: 3 | H39: 2ª | I39: SEGURANÇA | J39: Pessoas | K39: 1000
B40: 5.3 | C40: Testar sincronização correta dos dados | D40: 5.3 | E40: 45894 | F40: 45896 | G40: 3 | H40: 1ª | I40: SEGURANÇA | J40: Pessoas | K40: 1000
B41: 6 | C41: Testes | D41: 5.3 | K41: =SUM(K38:K40) -> 5000
B42: 6.1 | C42: Testes de qualidade e desempenho | D42: 5.1 | E42: 45892 | F42: 45893 | G42: 2 | H42: 1ª | I42: QUALIDADE | J42: Pessoas | K42: 7500
B43: 6.2 | C43: Teste de usabilidade com usuários | D43: 6.1 | E43: 45893 | F43: 45894 | G43: 2 | H43: 1ª | I43: QUALIDADE | J43: Pessoas | K43: 2600
B44: 6.3 | C44: Correção de bugs e problemas de interface | D44: 6.2 | E44: 45894 | F44: 45895 | G44: 2 | H44: 1ª | I44: QUALIDADE | J44: Pessoas | K44: 1500
B45: 7 | C45: Lançamento (Stakeholders internos) | D45: 6.1 | K45: =SUM(K42:K44) -> 11600
B46: 7.1.1 | C46: Preparar infraestrutura de implantação | D46: 6.3 | E46: 45894 | F46: 45895 | G46: 2 | H46: 2ª | I46: REDES | J46: Pessoas | K46: 7500
B47: 7.1.2 | C47: Criar materiais de treinamento e demonstração | D47: 7.1.1 | E47: 45896 | F47: 45897 | G47: 2 | H47: 2ª | I47: COMERCIAL | J47: Pessoas | K47: 6600
A48: . | B48: 7.1.3 | C48: Implantar em produção (uso interno) | D48: 7.1.2 | E48: 45898 | F48: 45899 | G48: 2 | H48: 2ª | I48: COMERCIAL | J48: Pessoas | K48: 4500
B49: 8 | C49: Pós-lançamento (Stakeholders internos) | D49: 7.1.3 | K49: =SUM(K46:K48) -> 18600
B50: 8.1.1 | C50: Monitorar feedback e métricas de uso | D50: 7.1.3 | E50: 45900 | F50: 45905 | G50: 6 | H50: 2ª | I50: EQUIPE TÉCNICA | J50: Pessoas | K50: 5000
B51: 8.1.2 | C51: Realizar atualizações periódicas | D51: 7.1.3 | E51: 45900 | F51: 45905 | G51: 6 | H51: 2ª | I51: EQUIPE TÉCNICA | J51: Pessoas | K51: 4000
B52: 8.1.3 | C52: Suporte ao usuário (dúvidas e problemas) | D52: 7.1.3 | E52: 45900 | F52: 45905 | G52: 6 | H52: 2ª | I52: EQUIPE TÉCNICA | J52: Pessoas | K52: 2000
B53: 9 | C53: Marketing e Divulgação - para o Mercado | D53: 8.1.3 | K53: =SUM(K50:K52) -> 11000
B54: 9.1.1 | C54: Estratégias de comunicação para adoção | D54: 8.1.3 | E54: 06/09/20255 | F54: 45911 | G54: 6 | H54: 2ª | I54: EQUIPE TÉCNICA | J54: Pessoas | K54: 3500
B55: 9.1.2 | C55: Engajar key users e stakeholders | D55: 9.1.1 | E55: 06/09/20255 | F55: 45911 | G55: 6 | H55: 2ª | I55: EQUIPE TÉCNICA | J55: Pessoas | K55: 2500
B56: 9.1.3 | C56: Comunicação interna e externa dos benefícios | D56: 9.1.2 | E56: 06/09/20255 | F56: 45911 | G56: 6 | H56: 2ª | I56: EQUIPE TÉCNICA | J56: Pessoas | K56: 9000
B57: 10 | C57: Avaliação e Aperfeiçoamento | D57: 9.1.3 | K57: =SUM(K54:K56) -> 15000
B58: 10.1.1 | C58: Análises regulares de desempenho e impacto | D58: 9.1.3 | E58: 45881 | F58: 45886 | G58: 6 | H58: 2ª | I58: DESEMPENHO | J58: Pessoas | K58: 4000
B59: 10.1.2 | C59: Coletar feedback e implementar melhorias | D59: 10.1.1 | E59: 45887 | F59: 45892 | G59: 6 | H59: 2ª | I59: COMERCIAL | J59: Pessoas | K59: 2600
B60: 10.1.3 | C60: Adaptação às necessidades de negócio | D60: 10.1.2 | E60: 45893 | F60: 45898 | G60: 6 | H60: 2ª | I60: COMERCIAL | J60: Pessoas | K60: 2300
B61: 11 | C61: Expansão | D61: 10.1.3 | K61: =SUM(K58:K60) -> 8900
B62: 11.1 | C62: Análise de expansão de funcionalidades/mercados | D62: 10.1.3 | E62: 45899 | F62: 45904 | G62: 6 | H62: 2ª | I62: EQUIPE TÉCNICA | J62: Pessoas | K62: 3700
B63: 11.1.2 | C63: Novas integrações ou parcerias estratégicas | D63: 10.1.3 | E63: 45899 | F63: 45904 | G63: 6 | H63: 2ª | I63: EQUIPE TÉCNICA | J63: Pessoas | K63: 8500
B64: 11.1.3 | C64: Recursos avançados / versão premium | D64: 10.1.3 | E64: 45899 | F64: 45904 | G64: 6 | H64: 2ª | I64: EQUIPE TÉCNICA | J64: Pessoas | K64: 2800
D65: 11.1.3 | K65: =SUM(K62:K64) -> 15000
D66: TOTAL | K66: =SUM(K14+K22+K29+K37+I71+G69+K45+K49+K53+K57+K61+K65) -> 150000

Sheet WBS_Detalhado (ordem depend)
B6: 4.2 Plano de ação detalhado da WBS (com dependência, tempo e recurso)
B8: Ref | C8: Etapas – Atividades - | D8: Dependência | E8: Duração em dias | F8: Conclusão | G8: Responsável | H8: Recursos | I8: Obs
B9: 1.1 | C9: Definir os objetivos do dashboard e proposta de valor | D9: 1.1 | E9: 4 | F9: 2ª | G9: GERENTE DE PROJETO | H9: Pessoas | I9: -
B10: 1.2 | C10: Identificar funcionalidades principais (campanhas, clientes, pedidos) | D10: 1.1 | E10: 4 | F10: 2ª | G10: GERENTE DE PROJETO | H10: Pessoas | I10: -
B11: 1.3 | C11: Formar equipe de desenvolvimento e design | D11: 1.2 | E11: 4 | F11: 2ª | G11: GERENTE DE PROJETO | H11: Pessoas
B12: 2.1 | C12: Análise de mercado (concorrentes e demandas) | D12: 2.0 | E12: 4 | F12: 2ª | G12: GERENTE DE PROJETO | H12: Pessoas
B13: 2.2 | C13: Definir requisitos detalhados (escopo) | D13: 1.2 | E13: 4 | F13: 2ª | G13: GERENTE DE PROJETO | H13: Pessoas
B14: 2.2.1 | C14: Requisitos para Campanhas (winback, loyalty, seasonal etc.) | D14: 2.2 | E14: 3 | F14: 2ª | G14: GERENTE DE PROJETO | H14: Pessoas | I14: -
B15: 2.2.2 | C15: Requisitos para Clientes (perfil, status, enriquecimento) | D15: 2.2 | E15: 2 | F15: 2ª | G15: GERENTE DE PROJETO | H15: Pessoas | I15: -
B16: 2.2.3 | C16: Requisitos para Pedidos (delivery, indoor, takeout) | D16: 2.2 | E16: 2 | F16: 1ª | G16: GERENTE DE PROJETO | H16: Pessoas | I16: -
B17: 2.2.4 | C17: Requisitos de Integração (CampaignQueue, Customer, Order) | D17: 2.2 | E17: 3 | F17: 1ª | G17: GERENTE DE PROJETO | H17: Pessoas | I17: -
B18: 2.2.5 | C18: Criar cronograma detalhado | D18: 2.2 | E18: 2 | F18: 2ª | G18: GERENTE DE PROJETO | H18: Pessoas | I18: -
B19: 3.1 | C19: Design da Interface (UI) | D19: 1.3 | E19: 7 | F19: 1ª | G19: DESIGN | H19: Pessoas | I19: -
B20: 3.2 | C20: Experiência do usuário (UX) | D20: 3.1 | E20: 7 | F20: 1ª | G20: DESIGN | H20: Pessoas | I20: -
B21: 4.1 | C21: Estrutura do Dashboard (Front e Back-end) | D21: 3.2 | E21: 10 | F21: 2ª | G21: DESENVOLVIMENTO | H21: Pessoas | I21: -
B22: 4.2 | C22: Funcionalidades principais (Campanhas, Clientes, Pedidos) | D22: 4.1 | E22: 10 | F22: 2ª | G22: DESENVOLVIMENTO | H22: Pessoas | I22: -
B23: 5.1 | C23: Integração com CampaignQueue, Customer, Order | D23: 4.2 | E23: 3 | F23: 2ª | G23: SEGURANÇA | H23: Pessoas | I23: -
B24: 5.2 | C24: Segurança e privacidade de dados | D24: 5.1 | E24: 3 | F24: 2ª | G24: SEGURANÇA | H24: Pessoas | I24: -
B25: 5.3 | C25: Testar integração de dados | D25: 5.2 | E25: 3 | F25: 2ª | G25: SEGURANÇA | H25: Pessoas | I25: -
... B40: 11.3 | C40: Recursos avançados/premium do dashboard | D40: 11.2 | E40: 4 | F40: 2ª | G40: EQUIPE TÉCNICA | H40: Pessoas | I40: -

Sheet SAM SRM
A1: Entregas do Projeto | B1: A definir | C1: Atulizado Em | D1: 45901
A3: SAM | I3: SRM
A4: Stakeholder | B4: Objetivos | C4: Metas | D4: Motivações e Interesses | E4: Poder e influência | F4: Importância e Impacto | G4: Papéis & Responsabilidades | H4: Sintonia "fina" | I4: Área de Interesse | J4: Nível de Detalhe | K4: Formato | L4: Frequência | M4: Mecanismo de Entrega
A5: Cliente (Usuários Finais) | B5: Acessar KPIs personalizados e gráficos interativos. | C5: Melhorar a tomada de decisão individual com base nos dados da plataforma. | D5: Obter informações relevantes de forma rápida e visual. | E5: Influência moderada via uso e feedback, mas sem poder de decisão. | F5: Alto impacto na aceitação do sistema. | G5: Utilizar o dashboard conforme seu perfil (cliente), fornecer feedback. | H5: Feedback contínuo e coleta de sugestões | I5: Funcionalidades, performance e usabilidade do sistema | J5: Médio – informações claras e objetivas. | K5: Visual e Interativo | L5: Mensal ou por entregas de versões | M5: Email + Sessões de demonstração
A6: Product Owner | B6: Garantir que o produto final atenda às necessidades do negócio. | C6: Entrega funcional e validada do sistema dentro do escopo. | D6: Alinhar entregas com os objetivos estratégicos da empresa/plataforma. | E6: Determina a direção e as prioridades do Alto poder sobre decisões de escopo e prioridades.. | F6: Altíssimo – garante alinhamento entre produto e negócio. | G6: Priorização de funcionalidades, definição de requisitos. | H6: Comunicação diária com a equipe | I6: Produto e backlog | J6: Alto – precisa de visão técnica e estratégica. | K6: Relatórios e dashboards | L6: Semanal | M6: Reuniões + Trello/Jira
A7: Desenvolvedores | B7: Construir o sistema com qualidade técnica e dentro do prazo. | C7: Implementar os módulos com eficiência e segurança. | D7: Entregar um sistema funcional, escalável e bem documentado. | E7: Poder técnico elevado na implementação do sistema. | F7: Impacto direto na qualidade e entrega do projeto. | G7: Codificar, integrar, testar e corrigir o sistema. | H7: Alinhamento com PO e UX | I7: Lógica do sistema e integração | J7: Alto – requerem detalhes técnicos completos. | K7: Documentação técnica | L7: Diária | M7: Reuniões de stand-up + GitHub
A8: Time Comercial | B8: Obter dados estratégicos para apoiar vendas e relacionamento. | C8: Usar o dashboard para análise de resultados de campanhas. | D8: Melhorar performance de vendas e retenção. | E8: Influência média em requisitos voltados a vendas. | F8: Importante para direcionar funcionalidades úteis ao negócio. | G8: Usar dados para planejar ações comerciais. | H8: Acesso a KPIs e relatórios | I8: Métricas de conversão, canais e clientes | J8: Médio – foco em métricas e relatórios. | K8: Relatórios e dashboards | L8: Mensal | M8: PDF ou Excel via e-mail
A9: Marketing | B9: Planejar campanhas mais eficientes com base em dados. | C9: Aumentar engajamento com base nos insights da plataforma. | D9: Usar visualizações e alertas inteligentes para campanhas. | E9: Influência moderada com foco em engajamento. | F9: Relevante para campanhas e estratégias de retenção. | G9: Definir critérios de segmentação, interpretar dados de comportamento. | H9: Alinhamento com Product Owner | I9: Engajamento, canais e comportamento de uso | J9: Médio – dados analíticos e insights visuais. | K9: Dashboards e KPIs | L9: Quinzenal | M9: Plataforma + relatórios por e-mail
A10: UX (User Experience) | B10: Garantir que o sistema seja intuitivo e responsivo. | C10: Reduzir fricções na jornada do usuário. | D10: Oferecer uma boa experiência para retenção e satisfação. | E10: Poder sobre decisões de usabilidade. | F10: Impacto alto na experiência e aceitação do sistema. | G10: Criar protótipos, testes de usabilidade, validar interfaces. | H10: Iterações constantes com dev e PO | I10: Navegação, responsividade e acessibilidade | J10: Alto – detalhes sobre fluxo e comportamento do usuário. | K10: Protótipos e relatórios de testes | L10: A cada sprint | M10: Figma + reuniões de revisão
A11: Equipe de Suporte ao Cliente | B11: Ajudar clientes a utilizarem o dashboard corretamente. | C11: Reduzir número de chamados e dúvidas. | D11: Garantir que os usuários entendam as funcionalidades. | E11: Influência baixa, mas relevante para melhorias contínuas. | F11: Importância média na experiência pós-entrega. | G11: Responder dúvidas, criar materiais de ajuda. | H11: Alinhamento com UX e PO | I11: Funcionalidades e dúvidas frequentes | J11: Médio – foco em funcionamento prático e dúvidas. | K11: Tutoriais e FAQs | L11: Contínuo | M11: Central de ajuda + e-mail
A12: Gerência Executiva/Alta Administração | B12: Avaliar resultados estratégicos e ROI da plataforma. | C12: Acompanhar KPIs-chave e justificar investimentos. | D12: Ter visão consolidada e estratégica da operação. | E12: Alto poder de decisão estratégica e orçamentária. | F12: Crítico – define o futuro do projeto. | G12: Tomar decisões com base em dados, aprovar escopo e recursos. | H12: Apresentações formais e relatórios executivos | I12: Estratégia e retorno sobre investimento | J12: Baixo – visão executiva e resultados consolidados. | K12: Relatórios executivos e gráficos resumidos | L12: Mensal | M12: PDF + reuniões de apresentação

Sheet Diagrama de Seta
A1: Projeto para construir uma casa | AA1: Diagrama de seta
AB2: Atividade fantasma
B3: Quantos Dias dura o projeto?
Z4: Dias
A5: Rede de Precedência de Atividades | Z5: 1 | AA5: 2 | AB5: 3 | AC5: 4 | AD5: 5 | AE5: 6 | AF5: 7 | AG5: 8 | AH5: 9 | AI5: 10 | AJ5: 11 | AK5: 12 | AL5: 13 | AM5: 14 | AN5: 15 | AO5: 16 | AP5: 17 | AQ5: 18 | AR5: 19 | AS5: 20 | AT5: 21 | AU5: 22 | AV5: 23 | AW5: 24 | AX5: 25 | AY5: 26 | AZ5: 27 | BA5: 28 | BB5: 29 | BC5: 30 | BD5: 31 | BE5: 32 | BF5: 33 | BG5: 34 | BH5: 35 | BI5: 36 | BJ5: 37 | BK5: 38 | BL5: 39 | BM5: 40 | BN5: 41 | BO5: 42 | BP5: 43 | BQ5: 44 | BR5: 45 | BS5: 46 | BT5: 47 | BU5: 48 | BV5: 49 | BW5: 50 | BX5: 51 | BY5: 52 | BZ5: 53 | CA5: 54 | CB5: 55 | CC5: 56 | CD5: 57 | CE5: 58 | CF5: 59 | CG5: 60 | CH5: 61 | CI5: 62 | CJ5: 63 | CK5: 64 | CL5: 65 | CM5: 66 | CN5: 67 | CO5: 68 | CP5: 69 | CQ5: 70 | CR5: 71 | CS5: 72 | CT5: 73 | CU5: 74 | CV5: 75 | CW5: 76 | CX5: 77 | CY5: 78 | CZ5: 79 | DA5: 80 | DB5: 81
B6: Atividades | C6: Dependência | D6: Duração em dias | AJ6: 3
A7: 1 | B7: Definir objetivos do dashboard | C7: NÃO | D7: 4 | AR7: 11 | AY7: 12 | BC7: 13 | BM7: 14 | BW7: 15 | BZ7: 16 | CC7: 17 | CG7: 18 | CJ7: 19 | CP7: 20 | CV7: 21 | DB7: 22
A8: 2 | B8: Identificar funcionalidades principais | C8: 1 | D8: 4 | Z8: 1 | AE8: 2 | AK8: 4 | AN8: 6 | AQ8: 9 | AS8: 10
A9: 3 | B9: Formar equipe de desenvolvimento e design | C9: 2 | D9: 4 | AK9: 5
A10: 4 | B10: Análise de mercado | C10: 2 | D10: 4 | AM10: 7
A11: 5 | B11: Definir requisitos detalhados (escopo) | C11: 2 | D11: 4 | AM11: 8
A12: 6 | B12: Requisitos - Campanhas | C12: 4, 5 | D12: 3
A13: 7 | B13: Requisitos - Clientes | C13: 4, 5 | D13: 2
A14: 8 | B14: Requisitos - Pedidos | C14: 5 | D14: 2
A15: 9 | B15: Requisitos - Integração | C15: 6 | D15: 3 | Z15: Quantos dias dura o Projeto? 81
A16: 10 | B16: Criar cronograma detalhado | C16: 7, 8, 9 | D16: 2 | Z16: Quais as atividades não podem atrasar? 1, 2, 3, 11, 12, 13, 14, 15, 16, 17, 18, 19, 20, 21, 22 --> caminho crítico
A17: 11 | B17: Design da interface (UI) | C17: 3 | D17: 7 | Z17: A atividade 7 e 8 possuem 4 dias de folga
A18: 12 | B18: Experiência do usuário (UX) | C18: 11 | D18: 7 | Z18: A atividade 10 tem 10 dias de folga
A19: 13 | B19: Protótipos e testes de UI/UX | C19: 12 | D19: 4
A20: 14 | B20: Estrutura do dashboard (Front/Back-end) | C20: 10, 13 | D20: 10
A21: 15 | B21: Implementar funcionalidades (Campanhas/Clientes/Pedidos) | C21: 14 | D21: 10
A22: 16 | B22: Integração com sistemas (CampaignQueue, Customer, Order) | C22: 15 | D22: 3
A23: 17 | B23: Segurança e privacidade de dados | C23: 16 | D23: 3
A24: 18 | B24: Testes de qualidade e usabilidade | C24: 17 | D24: 4
A25: 19 | B25: Correções de bugs e interface | C25: 18 | D25: 3
A26: 20 | B26: Lançamento (infraestrutura + treinamento) | C26: 19 | D26: 6
A27: 21 | B27: Pós-lançamento (monitoramento e suporte) | C27: 20 | D27: 6
A28: 22 | B28: Avaliação, melhorias contínuas e expansão | C28: 21 | D28: 6

Sheet Diagrama de rede-precedência
A1: Projeto para construir uma casa | U1: PDI -Primeiro dia de início | X1: UDI - Último dia de início
U2: PDT - Primeito dia de término | X2: UDT - Último dia de término
B3: Quantos Dias dura o projeto? | U3: FL-Folgas Livres | X3: É o caminho crítico
U4: FT-Folgas totais
A6: Rede de Precedência de Atividades | T6: modelo
B7: Atividades | C7: Dependência | D7: Duração em dias | T7: atividade | U7: duração | Y7: Ativ, 3 | Z7: 4 | AC7: Ativ. 11 | AD7: 7 | AG7: Ativ. 12 | AH7: 7 | AK7: Ativ. 13 | AL7: 4
A8: 1 | B8: Definir objetivos do dashboard | C8: NÃO | D8: 4 | T8: PDI | U8: PDT | Y8: 8 | Z8: 12 | AC8: 12 | AD8: 19 | AG8: 19 | AH8: 26 | AK8: 26 | AL8: 30 | AP8: Ativ. 14 | AQ8: 10 | AS8: Ativ. 15 | AT8: 10 | AV8: Ativ. 16 | AW8: 3 | AY8: Ativ. 17 | AZ8: 3 | BB8: Ativ. 18 | BC8: 4 | BE8: Ativ. 19 | BF8: 3 | BH8: Ativ. 20 | BI8: 6 | BK8: Ativ. 21 | BL8: 6 | BN8: Ativ. 22 | BO8: 6
A9: 2 | B9: Identificar funcionalidades principais | C9: 1 | D9: 4 | T9: UDI | U9: UDT | Y9: 8 | Z9: 12 | AC9: 12 | AD9: 19 | AG9: 19 | AH9: 26 | AK9: 26 | AL9: 30 | AP9: 30 | AQ9: 40 | AS9: 40 | AT9: 50 | AV9: 50 | AW9: 53 | AY9: 53 | AZ9: 56 | BB9: 56 | BC9: 60 | BE9: 60 | BF9: 63 | BH9: 63 | BI9: 69 | BK9: 69 | BL9: 75 | BN9: 75 | BO9: 81
A10: 3 | B10: Formar equipe de desenvolvimento e design | C10: 2 | D10: 4 | T10: FL | U10: FT | Y10: 0 | Z10: 0 | AC10: 0 | AD10: 0 | AG10: 0 | AH10: 0 | AK10: 0 | AL10: 0 | AP10: 30 | AQ10: 40 | AS10: 40 | AT10: 50 | AV10: 50 | AW10: 53 | AY10: 53 | AZ10: 56 | BB10: 56 | BC10: 60 | BE10: 60 | BF10: 63 | BH10: 63 | BI10: 69 | BK10: 69 | BL10: 75 | BN10: 75 | BO10: 81
A11: 4 | B11: Análise de mercado | C11: 2 | D11: 4 | AP11: 0 | AQ11: 0 | AS11: 0 | AT11: 0 | AV11: 0 | AW11: 0 | AY11: 0 | AZ11: 0 | BB11: 0 | BC11: 0 | BE11: 0 | BF11: 0 | BH11: 0 | BI11: 0 | BK11: 0 | BL11: 0 | BN11: 0 | BO11: 0
A12: 5 | B12: Definir requisitos detalhados (escopo) | C12: 2 | D12: 4 | AD12: Ativ. 6 | AE12: 4 | AH12: Ativ. 9 | AI12: 3 | AL12: Ativ. 10 | AM12: 2
A13: 6 | B13: Requisitos - Campanhas | C13: 4, 5 | D13: 3 | S13: Ativ. 1 | T13: 4 | V13: Ativ. 2 | W13: 4 | Y13: Ativ. 4 | Z13: 4 | AD13: 12 | AE13: 15 | AH13: 15 | AI13: 18 | AL13: 18 | AM13: 20
A14: 7 | B14: Requisitos - Clientes | C14: 4, 5 | D14: 2 | S14: 0 | T14: 4 | V14: 4 | W14: 8 | Y14: 8 | Z14: 12 | AD14: 16 | AE14: 19 | AH14: 19 | AI14: 22 | AL14: 22 | AM14: 24
A15: 8 | B15: Requisitos - Pedidos | C15: 5 | D15: 2 | S15: =T15-T13 -> 0 | T15: 4 | V15: 4 | W15: 8 | Y15: 12 | Z15: 16 | AD15: 4 | AE15: 4 | AH15: 4 | AI15: 4 | AL15: 4 | AM15: 4
A16: 9 | B16: Requisitos - Integração | C16: 6 | D16: 3 | S16: =S15-S14 -> 0 | T16: =T15-T14 -> 0 | V16: 0 | W16: 0 | Y16: 4 | Z16: 4
A17: 10 | B17: Criar cronograma detalhado | C17: 7, 8, 9 | D17: 2 | AD17: Ativ. 7 | AE17: 3
A18: 11 | B18: Design da interface (UI) | C18: 3 | D18: 7 | AD18: 12 | AE18: 14
A19: 12 | B19: Experiência do usuário (UX) | C19: 11 | D19: 7 | Y19: Ativ. 5 | Z19: 4 | AD19: 16 | AE19: 18
A20: 13 | B20: Protótipos e testes de UI/UX | C20: 12 | D20: 4 | Y20: 8 | Z20: 12 | AD20: 4 | AE20: 4
A21: 14 | B21: Estrutura do dashboard (Front/Back-end) | C21: 10, 13 | D21: 10 | Y21: 12 | Z21: 16
A22: 15 | B22: Implementar funcionalidades (Campanhas/Clientes/Pedidos) | C22: 14 | D22: 10 | Y22: 4 | Z22: 4 | AD22: Ativ. 8 | AE22: 2
A23: 16 | B23: Integração com sistemas (CampaignQueue, Customer, Order) | C23: 15 | D23: 3 | AD23: 12 | AE23: 14
A24: 17 | B24: Segurança e privacidade de dados | C24: 16 | D24: 3 | AD24: 16 | AE24: 18
A25: 18 | B25: Testes de qualidade e usabilidade | C25: 17 | D25: 4 | AD25: 4 | AE25: 4
A26: 19 | B26: Correções de bugs e interface | C26: 18 | D26: 3
A27: 20 | B27: Lançamento (infraestrutura + treinamento) | C27: 19 | D27: 6
A28: 21 | B28: Pós-lançamento (monitoramento e suporte) | C28: 20 | D28: 6
A29: 22 | B29: Avaliação, melhorias contínuas e expansão | C29: 21 | D29: 6

Sheet Orçamento
B2: Identificação do Projeto | D2: Mês
B3: Nome do Projeto | C3: =[4]Param!C17 -> Fidelize | E3: =[4]Param!C18 -> 45870 | F3: =DATE(YEAR(E3),MONTH(E3)+1,DAY(E3)) -> 45901 | G3: =DATE(YEAR(F3),MONTH(F3)+1,DAY(F3)) -> 45931 | H3: =DATE(YEAR(G3),MONTH(G3)+1,DAY(G3)) -> 45962 | I3: =DATE(YEAR(H3),MONTH(H3)+1,DAY(H3)) -> 45992 | J3: TOTAL
B4: Patrocinador | C4: =[4]Param!C19 -> Cannoli | D4: 0 | E4: 1 | F4: =E4+1 -> 2 | G4: =F4+1 -> 3 | H4: =G4+1 -> 4 | I4: =H4+1 -> 5
B5: Investimento inicial Total | C5: 150000 | D5: =SUM(D9+D11+D13+D15+D17+D19+D21+D23+D25+D27+D29) -> 155000 | E5: =SUM(#REF!)+E9+E11+E13+E15+E17+E19+E21+E23+E25+E27+E29 -> #REF! | F5: =SUM(#REF!)+F9+F11+F13+F15+F17+F19+F21+F23+F25+F27 -> #REF! | G5: =SUM(#REF!)+G9+G11+G13+G15+G17+G19+G21+G23+G25+G27 -> #REF! | H5: =SUM(#REF!)+H9+H11+H13+H15+H17+H19+H21+H23+H25+H27 -> #REF! | I5: =SUM(#REF!)+I9+I11+I13+I15+I17+I19+I21+I23+I25+I27 -> #REF! | J5: =SUM(D5:I5) -> #REF!
B6: Investimento Acumulado | C6: 0 | D6: =D5 -> 155000 | E6: =D6+E5 -> #REF! | F6: =E6+F5 -> #REF! | G6: =F6+G5 -> #REF! | H6: =G6+H5 -> #REF! | I6: =H6+I5 -> #REF!
B7: Orçado | C7: Explicação
B8: Investimento c/ taxa de crescimento | C8: Para facilitar o cálculo do gasto baseado em uma taxa de crescimento.
B9: Iniciação | C9: Gasto referente ao start do projeto, desde a definição dos objetivos do dashboard, identificação de funcionalidades principais (campanhas, clientes, pedidos) e formação de time. | D9: 7700 | E9: 3500 | F9: =E9*(1+F8) -> 3500 | G9: 500 | H9: 0 | I9: =H9*(1+I8) -> 0 | J9: =SUM(E9:I9) -> 7500
B10: Taxa de Crescimento de 10% | C10: Taxa de crescimento de investimento de 10% ao mês MOM | F10: 0.1 | G10: =F10 -> 0.1 | H10: =G10 -> 0.1 | I10: =H10 -> 0.1
B11: Planejamento | C11: Tudo que tange o mapeamento inicial do planejamento, incluindo análise de mercado e definição de requisitos detalhados para Campanhas (winback, loyalty), Clientes (perfil), Pedidos (delivery, indoor, takeout) e Integração com fontes de dados (Campaign, Customer, Order). | D11: 17000 | E11: 794.96 | F11: =E11*(1+F10) -> 874.456 | G11: =F11*(1+G10) -> 961.9016 | H11: =G11*(1+H10) -> 1058.0918 | I11: =H11*(1+I10) -> 1163.9009 | J11: =SUM(E11:I11) -> 4853.3103
B12: Taxa de Crescimento de 10% | C12: Taxa de crescimento de investimento de 10% ao mês MOM | F12: 0.1 | G12: =F12 -> 0.1 | H12: =G12 -> 0.1 | I12: =H12 -> 0.1
B13: Design e Prototipagem | C13: Todo processo que compete ao desenvolvimento da funcionalidade em sua camada de Wire, Layout, experiência (UX), incluindo Design da Interface (UI), criação de protótipos interativos e testes de UI/UX para o dashboard. | D13: 13200 | E13: 617.29 | F13: =E13*(1+F12) -> 679.019 | G13: =F13*(1+G12) -> 746.9209 | H13: =G13*(1+H12) -> 821.61299 | I13: =H13*(1+I12) -> 903.77429 | J13: =SUM(E13:I13) -> 3768.6172
B14: Taxa de Crescimento de 10% | C14: Taxa de crescimento de investimento de 10% ao mês MOM | F14: 0.1 | G14: =F14 -> 0.1 | H14: =G14 -> 0.1 | I14: =H14 -> 0.1
B15: Desenvolvimento | C15: Desenvolvimento da estrutura do dashboard (Front-end e Back-end) e implementação dos módulos principais (Campanhas, Clientes, Pedidos e Canais de Venda). | D15: 32000 | E15: 1496.43 | F15: =E15*(1+F14) -> 1646.073 | G15: =F15*(1+G14) -> 1810.6803 | H15: =G15*(1+H14) -> 1991.7483 | I15: =H15*(1+I14) -> 2190.9232 | J15: =SUM(E15:I15) -> 9135.8548
B16: Taxa de Crescimento de 10% | C16: Taxa de crescimento de investimento de 10% ao mês MOM | F16: 0.1 | G16: =F16 -> 0.1 | H16: =G16 -> 0.1 | I16: =H16 -> 0.1
B17: Integração com fontes de dados | C17: Foco na segurança e integração da plataforma, com a integração das fontes de dados CampaignQueue, Campaign, Customer e Order. | D17: 5000 | E17: 233.8 | F17: =E17*(1+F16) -> 257.18 | G17: =F17*(1+G16) -> 282.898 | H17: =G17*(1+H16) -> 311.1878 | I17: =H17*(1+I16) -> 342.30658 | J17: =SUM(E17:I17) -> 1427.3724
B18: Taxa de Crescimento de 10% | C18: Taxa de crescimento de investimento de 10% ao mês MOM | F18: 0.1 | G18: =F18 -> 0.1 | H18: =G18 -> 0.1 | I18: =H18 -> 0.1
B19: Teste | C19: Verificação das funcionalidades, realização de testes de qualidade, desempenho e usabilidade (com usuários reais/simulados) e correção de bugs e problemas de interface. | D19: 11600 | E19: 542.45 | F19: =E19*(1+F18) -> 596.695 | G19: =F19*(1+G18) -> 656.3645 | H19: =G19*(1+H18) -> 722.00095 | I19: =H19*(1+I18) -> 794.20105 | J19: =SUM(E19:I19) -> 3311.7115
B20: Taxa de Crescimento de 10% | C20: Taxa de crescimento de investimento de 10% ao mês MOM | F20: 0.1 | G20: =F20 -> 0.1 | H20: =G20 -> 0.1 | I20: =H20 -> 0.1
B21: Lançamento (Stakeholders internos) | C21: Preparação da infraestrutura de produção (implantação) e criação de materiais de treinamento e demonstração para stakeholders internos. | D21: 18600 | E21: 869.8 | F21: =E21*(1+F20) -> 956.78 | G21: =F21*(1+G20) -> 1052.458 | H21: =G21*(1+H20) -> 1157.7038 | I21: =H21*(1+I20) -> 1273.4742 | J21: =SUM(E21:I21) -> 5310.216
B22: Taxa de Crescimento de 10% | C22: Taxa de crescimento de investimento de 10% ao mês MOM | F22: 0.1 | G22: =F22 -> 0.1 | H22: =G22 -> 0.1 | I22: =H22 -> 0.1
B23: Pós-lançamento (Stakeholders internos) | C23: Monitoramento de feedback e métricas de uso, atualizações periódicas de funcionalidades e suporte ao usuário para solucionar dúvidas e problemas. | D23: 11000 | E23: 514.4 | F23: =E23*(1+F22) -> 565.84 | G23: =F23*(1+G22) -> 622.424 | H23: =G23*(1+H22) -> 684.6664 | I23: =H23*(1+I22) -> 753.13304 | J23: =SUM(E23:I23) -> 3140.4634
B24: Taxa de Crescimento de 10% | C24: Taxa de crescimento de investimento de 10% ao mês MOM | F24: 0.1 | G24: =F24 -> 0.1 | H24: =G24 -> 0.1 | I24: =H24 -> 0.1
B25: Marketing e Divulgação - para o Mercado | C25: Criação de estratégias de comunicação (interna e externa) para promover a adoção do dashboard e engajamento com key users e stakeholders externos. | D25: 15000 | E25: 701.45 | F25: =E25*(1+F24) -> 771.595 | G25: =F25*(1+G24) -> 848.7545 | H25: =G25*(1+H24) -> 933.62995 | I25: =H25*(1+I24) -> 1026.9929 | J25: =SUM(E25:I25) -> 4282.4224
B26: Taxa de Crescimento de 10% | C26: Taxa de crescimento de investimento de 10% ao mês MOM | F26: 0.1 | G26: =F26 -> 0.1 | H26: =G26 -> 0.1 | I26: =H26 -> 0.1
B27: Avaliação e Aperfeiçoamento | C27: Análises regulares de desempenho e impacto, coleta de feedback e implementação de melhorias contínuas e adaptação às necessidades de negócio. | D27: 8900 | E27: 416.2 | F27: =E27*(1+F26) -> 457.82 | G27: =F27*(1+G26) -> 503.602 | H27: =G27*(1+H26) -> 553.9622 | I27: =H27*(1+I26) -> 609.35842 | J27: =SUM(E27:I27) -> 2540.9426
B28: Taxa de Crescimento de 10% | C28: Taxa de crescimento de investimento de 10% ao mês MOM | F28: 0.1 | G28: =F28 -> 0.1 | H28: =G28 -> 0.1 | I28: =H28 -> 0.1
B29: Expansão | C29: Análise de expansão de funcionalidades e mercados, incluindo novas integrações ou parcerias estratégicas e desenvolvimento de recursos avançados/versão premium do dashboard. | D29: 15000 | E29: 701.45 | F29: =E29*(1+F28) -> 771.595 | G29: =F29*(1+G28) -> 848.7545 | H29: =G29*(1+H28) -> 933.62995 | I29: =H29*(1+I28) -> 1026.9929 | J29: =SUM(E29:I29) -> 4282.4224

Sheet Execução Orçamentária
B2: =Orçamento!B2 -> Identificação do Projeto | E2: Mês
B3: Nome do Projeto | C3: =[4]Param!C17 -> Fidelize | E3: =Orçamento!E3 -> 45870 | F3: =Orçamento!F3 -> 45901 | G3: =Orçamento!G3 -> 45931 | H3: =Orçamento!H3 -> 45962 | I3: =Orçamento!I3 -> 45992 | J3: TOTAL
B4: Patrocinador | C4: =[4]Param!C19 -> Cannoli | D4: 0 | E4: 1 | F4: =E4+1 -> 2 | G4: =F4+1 -> 3 | H4: =G4+1 -> 4 | I4: =H4+1 -> 5
B5: Investimento Total | D5: =SUM(D9+D11+D13+D15+D17+D19+D21+D23+D25+D27+D29) -> 158109 | E5: =SUM(E39:E52)+E9+E11+E13+E15+E17+E19+E21+E23+E25+E27+E29 -> 7987.4 | F5: =SUM(F9+F11+F13+F15+F17+F19+F21+F23+F25+F27+F29) -> 8708.14 | G5: =SUM(G9+G11+G13+G15+G17+G19+G21+G23+G25+G27+G29) -> 9500.954 | H5: =SUM(H9+H11+H13+H15+H17+H19+H21+H23+H25+H27+H29) -> 10373.049 | I5: =SUM(I9+I11+I13+I15+I17+I19+I21+I23+I25+I27+I29) -> 11332.354 | J5: =SUM(E5:I5) -> 47901.898
B6: Investimento Acumulado | D6: =D5 -> 158109 | E6: =D6+E5 -> 166096.4 | F6: =E6+F5 -> 174804.54 | G6: =F6+G5 -> 184305.49 | H6: =G6+H5 -> 194678.54 | I6: =H6+I5 -> 206010.9
B7: Realizado | C7: Explicação
B8: Investimento c/ taxa de crescimento
B9: =Orçamento!B9 -> Iniciação | C9: Gasto referente ao start do projeto, desde a definição dos objetivos do dashboard, identificação de funcionalidades principais (campanhas, clientes, pedidos) e formação de time. | D9: 9360 | E9: 780 | F9: =E9*(1+F8) -> 780 | G9: =F9*(1+G8) -> 780 | H9: =G9*(1+H8) -> 780 | I9: =H9*(1+I8) -> 780 | J9: =SUM(E9:I9) -> 3900
F10: 0.1 | G10: 0.1 | H10: 0.1 | I10: 0.1
B11: =Orçamento!B11 -> Planejamento | C11: Tudo que tange o mapeamento inicial do planejamento, incluindo análise de mercado e definição de requisitos detalhados para Campanhas (winback, loyalty), Clientes (perfil), Pedidos (delivery, indoor, takeout) e Integração com fontes de dados (Campaign, Customer, Order). | D11: 16680 | E11: 780 | F11: =E11*(1+F10) -> 858 | G11: =F11*(1+G10) -> 943.8 | H11: =G11*(1+H10) -> 1038.18 | I11: =H11*(1+I10) -> 1141.998 | J11: =SUM(E11:I11) -> 4761.978
F12: 0.1 | G12: =F12 -> 0.1 | H12: =G12 -> 0.1 | I12: =H12 -> 0.1
B13: =Orçamento!B13 -> Design e Prototipagem | C13: Todo processo que compete ao desenvolvimento da funcionalidade em sua camada de Wire, Layout, experiência (UX), incluindo Design da Interface (UI), criação de protótipos interativos e testes de UI/UX para o dashboard. | D13: 14969 | E13: 700 | F13: =E13*(1+F12) -> 770 | G13: =F13*(1+G12) -> 847 | H13: =G13*(1+H12) -> 931.7 | I13: =H13*(1+I12) -> 1024.87 | J13: =SUM(E13:I13) -> 4273.57
F14: 0.1 | G14: =F14 -> 0.1 | H14: =G14 -> 0.1 | I14: =H14 -> 0.1
B15: =Orçamento!B15 -> Desenvolvimento | C15: Desenvolvimento da estrutura do dashboard (Front-end e Back-end) e implementação dos módulos principais (Campanhas, Clientes, Pedidos e Canais de Venda). | D15: 32000 | E15: 1700 | F15: =E15*(1+F14) -> 1870 | G15: =F15*(1+G14) -> 2057 | H15: =G15*(1+H14) -> 2262.7 | I15: =H15*(1+I14) -> 2488.97 | J15: =SUM(E15:I15) -> 10378.67
F16: 0.1 | G16: =F16 -> 0.1 | H16: =G16 -> 0.1 | I16: =H16 -> 0.1
B17: =Orçamento!B17 -> Integração com fontes de dados | C17: Foco na segurança e integração da plataforma, com a integração das fontes de dados CampaignQueue, Campaign, Customer e Order. | D17: 5000 | E17: 203 | F17: =E17*(1+F16) -> 223.3 | G17: =F17*(1+G16) -> 245.63 | H17: =G17*(1+H16) -> 270.193 | I17: =H17*(1+I16) -> 297.2123 | J17: =SUM(E17:I17) -> 1239.3353
F18: 0.1 | G18: =F18 -> 0.1 | H18: =G18 -> 0.1 | I18: =H18 -> 0.1
B19: =Orçamento!B19 -> Teste | C19: Verificação das funcionalidades, realização de testes de qualidade, desempenho e usabilidade (com usuários reais/simulados) e correção de bugs e problemas de interface. | D19: 11600 | E19: 520 | F19: =E19*(1+F18) -> 572 | G19: =F19*(1+G18) -> 629.2 | H19: =G19*(1+H18) -> 692.12 | I19: =H19*(1+I18) -> 761.332 | J19: =SUM(E19:I19) -> 3174.652
F20: 0.1 | G20: =F20 -> 0.1 | H20: =G20 -> 0.1 | I20: =H20 -> 0.1
B21: =Orçamento!B21 -> Lançamento (Stakeholders internos) | C21: Preparação da infraestrutura de produção (implantação) e criação de materiais de treinamento e demonstração para stakeholders internos. | D21: 18600 | E21: 950 | F21: =E21*(1+F20) -> 1045 | G21: =F21*(1+G20) -> 1149.5 | H21: =G21*(1+H20) -> 1264.45 | I21: =H21*(1+I20) -> 1390.895 | J21: =SUM(E21:I21) -> 5799.845
F22: 0.1 | G22: =F22 -> 0.1 | H22: =G22 -> 0.1 | I22: =H22 -> 0.1
B23: =Orçamento!B23 -> Pós-lançamento (Stakeholders internos) | C23: Monitoramento de feedback e métricas de uso, atualizações periódicas de funcionalidades e suporte ao usuário para solucionar dúvidas e problemas. | D23: 11000 | E23: 514.4 | F23: =E23*(1+F22) -> 565.84 | G23: =F23*(1+G22) -> 622.424 | H23: =G23*(1+H22) -> 684.6664 | I23: =H23*(1+I22) -> 753.13304 | J23: =SUM(E23:I23) -> 3140.4634
F24: 0.1 | G24: =F24 -> 0.1 | H24: =G24 -> 0.1 | I24: =H24 -> 0.1
B25: =Orçamento!B25 -> Marketing e Divulgação - para o Mercado | C25: Criação de estratégias de comunicação (interna e externa) para promover a adoção do dashboard e engajamento com key users e stakeholders externos. | D25: 15000 | E25: 720 | F25: =E25*(1+F24) -> 792 | G25: =F25*(1+G24) -> 871.2 | H25: =G25*(1+H24) -> 958.32 | I25: =H25*(1+I24) -> 1054.152 | J25: =SUM(E25:I25) -> 4395.672
F26: 0.1 | G26: =F26 -> 0.1 | H26: =G26 -> 0.1 | I26: =H26 -> 0.1
B27: =Orçamento!B27 -> Avaliação e Aperfeiçoamento | C27: Análises regulares de desempenho e impacto, coleta de feedback e implementação de melhorias contínuas e adaptação às necessidades de negócio. | D27: 8900 | E27: 410 | F27: =E27*(1+F26) -> 451 | G27: =F27*(1+G26) -> 496.1 | H27: =G27*(1+H26) -> 545.71 | I27: =H27*(1+I26) -> 600.281 | J27: =SUM(E27:I27) -> 2503.091
F28: 0.1 | G28: =F28 -> 0.1 | H28: =G28 -> 0.1 | I28: =H28 -> 0.1
B29: =Orçamento!B29 -> Expansão | C29: Análise de expansão de funcionalidades e mercados, incluindo novas integrações ou parcerias estratégicas e desenvolvimento de recursos avançados/versão premium do dashboard. | D29: 15000 | E29: 710 | F29: =E29*(1+F28) -> 781 | G29: =F29*(1+G28) -> 859.1 | H29: =G29*(1+H28) -> 945.01 | I29: =H29*(1+I28) -> 1039.511 | J29: =SUM(E29:I29) -> 4334.621
B38: Investimentos
B39: =Orçamento!#REF! -> #REF! | D39: 0 | E39: 0 | F39: =E39 -> 0 | G39: =F39 -> 0 | H39: =G39 -> 0 | I39: =H39 -> 0 | J39: =I39 -> 0 | K39: =J39 -> 0 | L39: =K39 -> 0 | M39: =L39 -> 0 | ... P39: =O39 -> 0 | Q39: =SUM(D39:P39) -> 0
B40: =Orçamento!#REF! -> #REF! | F40: =E40 -> 0 | G40: =F40 -> 0 | H40: =G40 -> 0 | I40: =H40 -> 0 | J40: =I40 -> 0 | K40: =J40 -> 0 | L40: =K40 -> 0 | M40: =L40 -> 0 | ... P40: =O40 -> 0 | Q40: =SUM(D40:P40) -> 0
B41: =Orçamento!#REF! -> #REF! | F41: =E41 -> 0 | G41: =F41 -> 0 | H41: =G41 -> 0 | I41: =H41 -> 0 | J41: =I41 -> 0 | K41: =J41 -> 0 | L41: =K41 -> 0 | M41: =L41 -> 0 | ... P41: =O41 -> 0 | Q41: =SUM(D41:P41) -> 0
B42: =Orçamento!#REF! -> #REF! | F42: =E42 -> 0 | G42: =F42 -> 0 | H42: =G42 -> 0 | I42: =H42 -> 0 | J42: =I42 -> 0 | K42: =J42 -> 0 | L42: =K42 -> 0 | M42: =L42 -> 0 | ... P42: =O42 -> 0 | Q42: =SUM(D42:P42) -> 0
B43: =Orçamento!#REF! -> #REF! | F43: =E43 -> 0 | G43: =F43 -> 0 | H43: =G43 -> 0 | I43: =H43 -> 0 | J43: =I43 -> 0 | K43: =J43 -> 0 | L43: =K43 -> 0 | M43: =L43 -> 0 | ... P43: =O43 -> 0 | Q43: =SUM(D43:P43) -> 0
B44: =Orçamento!#REF! -> #REF! | F44: =E44 -> 0 | G44: =F44 -> 0 | H44: =G44 -> 0 | I44: =H44 -> 0 | J44: =I44 -> 0 | K44: =J44 -> 0 | L44: =K44 -> 0 | M44: =L44 -> 0 | ... P44: =O44 -> 0 | Q44: =SUM(D44:P44) -> 0
B45: =Orçamento!#REF! -> #REF! | F45: =E45 -> 0 | G45: =F45 -> 0 | H45: =G45 -> 0 | I45: =H45 -> 0 | J45: =I45 -> 0 | K45: =J45 -> 0 | L45: =K45 -> 0 | M45: =L45 -> 0 | ... P45: =O45 -> 0 | Q45: =SUM(D45:P45) -> 0
B46: =Orçamento!#REF! -> #REF! | F46: =E46 -> 0 | G46: =F46 -> 0 | H46: =G46 -> 0 | I46: =H46 -> 0 | J46: =I46 -> 0 | K46: =J46 -> 0 | L46: =K46 -> 0 | M46: =L46 -> 0 | ... P46: =O46 -> 0 | Q46: =SUM(D46:P46) -> 0
B47: =Orçamento!#REF! -> #REF! | F47: =E47 -> 0 | G47: =F47 -> 0 | H47: =G47 -> 0 | I47: =H47 -> 0 | J47: =I47 -> 0 | K47: =J47 -> 0 | L47: =K47 -> 0 | M47: =L47 -> 0 | ... P47: =O47 -> 0 | Q47: =SUM(D47:P47) -> 0
B48: =Orçamento!#REF! -> #REF! | F48: =E48 -> 0 | G48: =F48 -> 0 | H48: =G48 -> 0 | I48: =H48 -> 0 | J48: =I48 -> 0 | K48: =J48 -> 0 | L48: =K48 -> 0 | M48: =L48 -> 0 | ... P48: =O48 -> 0 | Q48: =SUM(D48:P48) -> 0
B49: =Orçamento!#REF! -> #REF! | F49: =E49 -> 0 | G49: =F49 -> 0 | H49: =G49 -> 0 | I49: =H49 -> 0 | J49: =I49 -> 0 | K49: =J49 -> 0 | L49: =K49 -> 0 | M49: =L49 -> 0 | ... P49: =O49 -> 0 | Q49: =SUM(D49:P49) -> 0
B50: =Orçamento!#REF! -> #REF! | F50: =E50 -> 0 | G50: =F50 -> 0 | H50: =G50 -> 0 | I50: =H50 -> 0 | J50: =I50 -> 0 | K50: =J50 -> 0 | L50: =K50 -> 0 | M50: =L50 -> 0 | ... P50: =O50 -> 0 | Q50: =SUM(D50:P50) -> 0
B51: =Orçamento!#REF! -> #REF! | F51: =E51 -> 0 | G51: =F51 -> 0 | H51: =G51 -> 0 | I51: =H51 -> 0 | J51: =I51 -> 0 | K51: =J51 -> 0 | L51: =K51 -> 0 | M51: =L51 -> 0 | ... P51: =O51 -> 0 | Q51: =SUM(D51:P51) -> 0
B52: =Orçamento!#REF! -> #REF! | F52: =E52 -> 0 | G52: =F52 -> 0 | H52: =G52 -> 0 | I52: =H52 -> 0 | J52: =I52 -> 0 | K52: =J52 -> 0 | L52: =K52 -> 0 | M52: =L52 -> 0 | ... P52: =O52 -> 0 | Q52: =SUM(D52:P52) -> 0
B57: Indicadores Financeiros
B59: NPV/VPL | D59: =NPV([4]Param!D4,E5:I5)+D5 -> #VALUE!
B60: Payback | D60: =COUNTIF(D6:I6,"<=0") -> 0
B61: ROI | D61: =SUM(E5:I5)/-D5 -> -0.30296756

Sheet Paramêtros
B2: Variável | C2: Tipo de Benefício | D2: Contexto
B3: Nome do projeto | C3: Projeto Fidelize Cannoli | D3: Focado em marketing para análise de estratégias. O projeto envolve a utilização de dados relevantes do Cannoli. | E3: .
B4: Escopo | C4: Desenvolvimento de um Dashboard Interativo | D4: Foco nas funcionalidades principais de Campanhas, Clientes e Pedidos. | E4: .
B5: Investimento (Valor Anonimizado) | C5: R$ 831mil por semestre | D5: Valor de investimento anonimizado mencionado na documentação do WBS. | E5: .
B6: Restrições (Limites) | C6: Tempo limitado de execução, acesso limitado, escopo limitado | D6: Restrições explícitas do projeto. | E6: .
B7: Exclusões | C7: Garantia de manutenção em produção contínua após o período acadêmico | D7: O que está fora do escopo. | E7: .
B8: Tecnologias principais | C8: Boas práticas e criptografia no código | D8: Referente às tecnologias utilizadas nos resultados. | E8: .
B15: Parametros a serem configurados inicialmente
B16: Projeto
B17: Nome do projeto | C17: Fidelize
B18: Mês de início | C18: 45870
B19: Patrocinador | C19: Cannoli

Sheet Capa
B5: Informações sobre o projeto
B6: Projeto | E6: Fidelize
B7: Gerente Responsável | E7: Marcella Santana
B8: Data da avaliação | E8: 45887
B9: Informações sobre a avaliação de riscos
B10: Projeto/Título | C10: FIDELIZE
B11: Gerente do Projeto | C11: Marcella Santana
B12: Data da Avaliação | C12: 45957
B13: Histórico da Avaliação de Riscos | C13: Avaliação inicial de riscos focada nas fases de Desenvolvimento e Integração de Dados.
B14: Comentário | C14: Baseado nos requisitos do 4º Semestre de Análise e Desenvolvimento de Sistemas (ADS) e nos dados simulados do Kit Cannoli.

Sheet Identificar riscos
A1: Identificação dos Riscos | AF1: Probabilidade | AI1: Impacto
A4: =Capa!E6 -> Fidelize
AF5: Muito Baixa - 1 | AG5: 1 | AI5: Muito Baixo - 1 | AJ5: 1
A6: ID | B6: Fase ou | D6: Declaração do Risco | H6: Severidade (X,Y) | AB6: Baixa - 2 | AC6: 2 | AE6: Muito Baixo - 2 | AF6: 2
B7: Recurso | C7: Classificação | D7: CAUSA (Começa a frase com "Como Resultado ...") | E7: RISCO (Começar a frase com "Pode ocorrer ...") | F7: CONSEQUÊNCIA (Começar a frase com "O que acarretaria ...") | G7: Riscos Colaterais | AB7: Moderada - 3 | AC7: 3 | AE7: Baixo - 3 | AF7: 3
A8: R01 | B8: Dados/Integração | C8: Dados Insuficientes | D8: Qualidade insatisfatória ou a presença de lacunas/inconsistências na base de dados fictícia do Kit Cannoli. | E8: Comprometimento da acurácia dos modelos de IA/ML (Alertas e Previsões). | F8: Falha na entrega de insights confiáveis, resultando em apoio estratégico inadequado para a Cannoli. | G8: Atraso no projeto e aumento nos custos | H8: ='Qualificar os riscos'!J8 -> #N/A | AB8: Alta - 4 | AC8: 4 | AE8: Baixo - 4 | AF8: 4
A9: R02 | B9: Desenvolvimento (ML Supervisionado) | C9: Inacurácia de IA | D9: Uso de um modelo simplificado (como Regressão Linear) ou entrada de variáveis defasadas para a funcionalidade de Previsão de Desempenho. | E9: O modelo de previsão apresentará um erro médio (MAE/RMSE) inaceitável, falhando em estimar valores futuros. | F9: A previsão será inadequada para apoiar decisões, exigindo o retrabalho do módulo ou sua exclusão do produto final. | G9: Atraso no projeto e desconfiança do cliente sobre resultados | H9: 0.07
A10: R03 | B10: Segurança/Integração | C10: Vulnerabilidade | D10: Falha ao implementar controles robustos de segurança e privacidade dos dados. | E10: Ocorrência de vazamento ou violação de dados de Customer, Order ou Campaign. | F10: Violação de requisitos não funcionais de segurança, acarretando perda de confiança ou exposição de dados anonimizados. | G10: Constante necessidade em reforçar a segurança dos dados | H10: 0.08
A11: R04 | B11: Escopo/Cronograma | C11: Limitações Estruturais | D11: Atrasos na entrega de módulos chave, como o Módulo de Pedidos e Canais de Venda, que possuem um prazo específico (23/08/2025 a 02/09/2025). | E11: O projeto excede as datas de entrega (22/set, 10/nov, 17/11, 25/11). | F11: O Sistema Final não estará pronto para as apresentações/entregáveis. | G11: Inacessibilidade do sistema como um todo | H11: 0.6

Sheet Quantificar os riscos
A1: Quantificação dos Riscos | AA1: Probabilidade | AD1: Impacto
A4: ='Identificar riscos'!A4 -> Fidelize
AA5: Muito Baixa - 1 | AB5: 1 | AD5: Muito Baixo - 1 | AE5: 1
A6: ID | B6: Declaração do Risco | F6: Impacto no Custo | G6: Impacto no Cronograma | H6: Observação | I6: Plano de Prevenção | J6: Plano de Contingência | AA6: Baixa - 2 | AB6: 2 | AD6: Muito Baixo - 2 | AE6: 2
B7: CAUSA (Começa a frase com "Como Resultado ...") | C7: RISCO (Começar a frase com "Pode ocorrer ...") | D7: CONSEQÜÊNCIA (Começar a frase com "O que acarretaria ...") | E7: Riscos Colaterais | AA7: Moderada - 3 | AB7: 3 | AD7: Baixo - 3 | AE7: 3
A8: =IF('Identificar riscos'!A8<>"",'Identificar riscos'!A8,"") -> R01 | B8: =IF('Identificar riscos'!D9<>"",'Identificar riscos'!D8,"") -> Qualidade insatisfatória ou a presença de lacunas/inconsistências na base de dados fictícia do Kit Cannoli. | C8: =IF('Identificar riscos'!E8<>"",'Identificar riscos'!E8,"") -> Comprometimento da acurácia dos modelos de IA/ML (Alertas e Previsões). | D8: =IF('Identificar riscos'!F8<>"",'Identificar riscos'!F8,"") -> Falha na entrega de insights confiáveis, resultando em apoio estratégico inadequado para a Cannoli. | E8: Atraso no projeto e aumento nos custos | F8: 10000 | G8: 5 | H8: Dias de atraso na implantação | I8: Implementar uma rotina de validação e limpeza de dados antes do treinamento dos modelos (verificação de duplicatas, nulos, outliers). | J8: Documentar as limitações dos dados no relatório final e ajustar o escopo das previsões. | AA8: Alta - 4 | AB8: 4 | AD8: Baixo - 4 | AE8: 4
A9: =IF('Identificar riscos'!A9<>"",'Identificar riscos'!A9,"") -> R02 | B9: =IF('Identificar riscos'!D9<>"",'Identificar riscos'!D9,"") -> Uso de um modelo simplificado (como Regressão Linear) ou entrada de variáveis defasadas para a funcionalidade de Previsão de Desempenho. | C9: =IF('Identificar riscos'!E9<>"",'Identificar riscos'!E9,"") -> O modelo de previsão apresentará um erro médio (MAE/RMSE) inaceitável, falhando em estimar valores futuros. | D9: =IF('Identificar riscos'!F9<>"",'Identificar riscos'!F9,"") -> A previsão será inadequada para apoiar decisões, exigindo o retrabalho do módulo ou sua exclusão do produto final. | E9: Atraso no projeto e desconfiança do cliente sobre resultados | F9: 10000 | G9: 5 | H9: Dias de atraso na implantação | I9: Criar pipeline de atualização de variáveis (verificação de defasagem semanal ou mensal). | J9: Se o modelo não atingir desempenho mínimo, trocar para modelo alternativo.
A10: =IF('Identificar riscos'!A10<>"",'Identificar riscos'!A10,"") -> R03 | B10: =IF('Identificar riscos'!D10<>"",'Identificar riscos'!D10,"") -> Falha ao implementar controles robustos de segurança e privacidade dos dados. | C10: =IF('Identificar riscos'!E10<>"",'Identificar riscos'!E10,"") -> Ocorrência de vazamento ou violação de dados de Customer, Order ou Campaign. | D10: =IF('Identificar riscos'!F10<>"",'Identificar riscos'!F10,"") -> Violação de requisitos não funcionais de segurança, acarretando perda de confiança ou exposição de dados anonimizados. | E10: Constante necessidade em reforçar a segurança dos dados | F10: 40000 | G10: 30 | H10: 1 mês de atraso | I10: Fazer testes de vulnerabilidade e revisões de segurança antes da implantação. | J10: Em caso de violação, acionar imediatamente o plano de resposta a incidentes e isolar o ambiente afetado.
A11: =IF('Identificar riscos'!A11<>"",'Identificar riscos'!A11,"") -> R04 | B11: =IF('Identificar riscos'!D11<>"",'Identificar riscos'!D11,"") -> Atrasos na entrega de módulos chave, como o Módulo de Pedidos e Canais de Venda, que possuem um prazo específico (23/08/2025 a 02/09/2025). | C11: =IF('Identificar riscos'!E11<>"",'Identificar riscos'!E11,"") -> O projeto excede as datas de entrega (22/set, 10/nov, 17/11, 25/11). | D11: =IF('Identificar riscos'!F11<>"",'Identificar riscos'!F11,"") -> O Sistema Final não estará pronto para as apresentações/entregáveis. | E11: Inacessibilidade do sistema como um todo | F11: 25000 | G11: 5~10 | H11: Dias de atraso na implantação | I11: Realizar testes de integração contínua para reduzir retrabalho ao juntar os módulos. | J11: Caso o atraso seja inevitável, negociar nova data de apresentação parcial com o patrocinador.

Sheet Qualificar os riscos
A1: Qualificação dos Riscos | AE1: Probabilidade | AH1: Impacto
K2: Base Custo | M2: 10000 | N2: R$
K3: Base Prazo | M3: 30 | N3: dias úteis
A4: ='Identificar riscos'!A4 -> Fidelize
AE5: Muito Baixa - 1 | AF5: 1 | AH5: Muito Baixo - 1 | AI5: 1
A6: ID | B6: Declaração do Risco | E6: Probabilidade do risco virar incidente (Y) | F6: Avaliação de Impacto (X) | J6: Severidade (Y,X) | L6: Custo | M6: Prazo | AE6: Baixa - 2 | AF6: 2 | AH6: Muito Baixo - 2 | AI6: 2
B7: CAUSA (Começa a frase com "Como Resultado ...") | C7: RISCO (Começar a frase com "Pode ocorrer ...") | D7: CONSEQÜÊNCIA (Começar a frase com "O que acarretaria ...") | F7: Aumento no Custo (X1) | G7: Desvio no Cronograma (X2) | H7: (X1*X2) | I7: Resultado do Impacto (X1+X2) | K7: Riscos Colaterais | AE7: Moderada - 3 | AF7: 3 | AH7: Baixo - 3 | AI7: 3
A8: =IF('Identificar riscos'!A8<>"",'Identificar riscos'!A8,"") -> R01 | B8: =IF('Identificar riscos'!D8<>"",'Identificar riscos'!D8,"") -> Qualidade insatisfatória ou a presença de lacunas/inconsistências na base de dados fictícia do Kit Cannoli. | C8: =IF('Identificar riscos'!E8<>"",'Identificar riscos'!E8,"") -> Comprometimento da acurácia dos modelos de IA/ML (Alertas e Previsões). | D8: =IF('Identificar riscos'!F8<>"",'Identificar riscos'!F8,"") -> Falha na entrega de insights confiáveis, resultando em apoio estratégico inadequado para a Cannoli. | E8: Alta - 0,4 | F8: Entre 10% e 20% - 1,40 | G8: Insignificante - 2,05 | H8: =IF(F8<>"",IF(G8<>"",RIGHT(F8,4)*RIGHT(G8,4),""),"") -> 2.87 | I8: =IF(H8<>"",VLOOKUP(H8,'Sensibilidade ao Risco'!$E$2:$F$5,2,FALSE),"") -> #N/A | J8: =IF(E8<>"",IF(I8<>"",(RIGHT(I8,3))*(RIGHT(E8,3)),""),"") -> #N/A | K8: Atraso no projeto e aumento nos custos | L8: =ROUNDUP('Quantificar os riscos'!F8/'Qualificar os riscos'!$M$2,2) -> 1 | M8: =ROUNDUP('Quantificar os riscos'!G8/'Qualificar os riscos'!$M$3,2) -> 0.17 | AE8: Alta - 4 | AF8: 4 | AH8: Baixo - 4 | AI8: 4
A9: =IF('Identificar riscos'!A9<>"",'Identificar riscos'!A9,"") -> R02 | B9: =IF('Identificar riscos'!D9<>"",'Identificar riscos'!D9,"") -> Uso de um modelo simplificado (como Regressão Linear) ou entrada de variáveis defasadas para a funcionalidade de Previsão de Desempenho. | C9: =IF('Identificar riscos'!E9<>"",'Identificar riscos'!E9,"") -> O modelo de previsão apresentará um erro médio (MAE/RMSE) inaceitável, falhando em estimar valores futuros. | D9: =IF('Identificar riscos'!F9<>"",'Identificar riscos'!F9,"") -> A previsão será inadequada para apoiar decisões, exigindo o retrabalho do módulo ou sua exclusão do produto final. | E9: Muito baixa - 0,05 | F9: Maior que 20% - 1,80 | G9: Entre 5% e 10% - 2,20 | H9: =IF(F9<>"",IF(G9<>"",RIGHT(F9,4)*RIGHT(G9,4),""),"") -> 3.96 | I9: =IF(H9<>"",VLOOKUP(H9,'Sensibilidade ao Risco'!$E$2:$F$5,2,FALSE),"") -> #N/A | J9: =IF(E9<>"",IF(I9<>"",(RIGHT(I9,3))*(RIGHT(E9,3)),""),"") -> #N/A | K9: Atraso no projeto e desconfiança do cliente sobre resultados | L9: =ROUNDUP('Quantificar os riscos'!F9/'Qualificar os riscos'!$M$2,2) -> 1 | M9: =ROUNDUP('Quantificar os riscos'!G9/'Qualificar os riscos'!$M$3,2) -> 0.17
A10: =IF('Identificar riscos'!A10<>"",'Identificar riscos'!A10,"") -> R03 | B10: =IF('Identificar riscos'!D10<>"",'Identificar riscos'!D10,"") -> Falha ao implementar controles robustos de segurança e privacidade dos dados. | C10: =IF('Identificar riscos'!E10<>"",'Identificar riscos'!E10,"") -> Ocorrência de vazamento ou violação de dados de Customer, Order ou Campaign. | D10: =IF('Identificar riscos'!F10<>"",'Identificar riscos'!F10,"") -> Violação de requisitos não funcionais de segurança, acarretando perda de confiança ou exposição de dados anonimizados. | E10: Moderada - 0,2 | F10: Maior que 20% - 1,80 | G10: Entre 10% e 20% - 2,40 | H10: =IF(F10<>"",IF(G10<>"",RIGHT(F10,4)*RIGHT(G10,4),""),"") -> 4.32 | I10: =IF(H10<>"",VLOOKUP(H10,'Sensibilidade ao Risco'!$E$2:$F$5,2,FALSE),"") -> #N/A | J10: =IF(E10<>"",IF(I10<>"",(RIGHT(I10,3))*(RIGHT(E10,3)),""),"") -> #N/A | K10: Constante necessidade em reforçar a segurança dos dados | L10: =ROUNDUP('Quantificar os riscos'!F10/'Qualificar os riscos'!$M$2,2) -> 4 | M10: =ROUNDUP('Quantificar os riscos'!G10/'Qualificar os riscos'!$M$3,2) -> 1
A11: =IF('Identificar riscos'!A11<>"",'Identificar riscos'!A11,"") -> R04 | B11: =IF('Identificar riscos'!D11<>"",'Identificar riscos'!D11,"") -> Atrasos na entrega de módulos chave, como o Módulo de Pedidos e Canais de Venda, que possuem um prazo específico (23/08/2025 a 02/09/2025). | C11: =IF('Identificar riscos'!E11<>"",'Identificar riscos'!E11,"") -> O projeto excede as datas de entrega (22/set, 10/nov, 17/11, 25/11). | D11: =IF('Identificar riscos'!F11<>"",'Identificar riscos'!F11,"") -> O Sistema Final não estará pronto para as apresentações/entregáveis. | E11: Muito baixa - 0,05 | F11: Menor que 5% - 1,10 | G11: Entre 10% e 20% - 2,40 | H11: =IF(F11<>"",IF(G11<>"",RIGHT(F11,4)*RIGHT(G11,4),""),"") -> 2.64 | I11: =IF(H11<>"",VLOOKUP(H11,'Sensibilidade ao Risco'!$E$2:$F$5,2,FALSE),"") -> #N/A | J11: =IF(E11<>"",IF(I11<>"",(RIGHT(I11,3))*(RIGHT(E11,3)),""),"") -> #N/A | K11: Inacessibilidade do sistema como um todo | L11: =ROUNDUP('Quantificar os riscos'!F11/'Qualificar os riscos'!$M$2,2) -> 2.5 | M11: =ROUNDUP('Quantificar os riscos'!G11/'Qualificar os riscos'!$M$3,2) -> #VALUE!
F31: Insignificante - 1,05 | G31: Insignificante - 2,05 | H31: Muito baixa - 0,05
F32: Menor que 5% - 1,10 | G32: Menor que 5% - 2,10 | H32: Baixa - 0,1
F33: Entre 5% e 10% - 1,20 | G33: Entre 5% e 10% - 2,20 | H33: Moderada - 0,2
F34: Entre 10% e 20% - 1,40 | G34: Entre 10% e 20% - 2,40 | H34: Alta - 0,4
F35: Maior que 20% - 1,80 | G35: Maior que 20% - 2,80 | H35: Muito Alta - 0,8

Sheet Sensibilidade ao Risco
A1: Custo | B1: Peso1 | C1: Cronograma | D1: Peso2 | E1: Peso1 X Peso2 | F1: Impacto
A2: Aumento de custo insignificante | B2: 2.3 | C2: Desvio no cronograma insignificante | D2: 2.05 | E2: =B2*D2 -> 4.715 | F2: Alta - 0,40
A3: Aumento de custo significante | B3: 2.4 | C3: Desvio menor que 5% no cronograma | D3: 2.1 | E3: =B3*D3 -> 5.04 | F3: Baixa - 0,10
A4: Aumento de custo significante | B4: 1.05 | C4: Desvio total entre 5% e 10% no cronograma | D4: 2.2 | E4: =B4*D4 -> 2.31 | F4: Baixa - 0,10
A5: Aumento de custo significante | B5: 1.05 | C5: Desvio total entre 10% e 20% no cronograma | D5: 2.4 | E5: =B5*D5 -> 2.52 | F5: Moderada - 0,20
A6: Muito baixa - 0,05
A7: Baixa - 0,10
A8: Moderada - 0,20
A9: Alta - 0,40
A10: Muito Alta - 0,80

Sheet Plano de Comunicação
A1: 1. Identificação das principais partes interessadas no projeto (stakeholders do projeto)
A3: Quadro 01. Matriz Interesse versus Poder para o projeto
A5: Identificação Stakeholder | B5: Nível de Interesse no projeto | C5: Nível de poder no projeto | D5: Explicar a ação a ser tomada: | G5: Plano de Comunicação
A6: Cliente (Usuários Finais) | B6: Acessar KPIs personalizados e gráficos interativos. Melhorar a tomada de decisão individual com base nos dados da plataforma. Obter informações relevantes de forma rápida e visual. | C6: Influência moderada via uso e feedback, mas sem poder de decisão. | D6: Usar o aplicativo, fornecer feedback, compartilhar experiências. | G6: Data: 02/08/2025 Projeto: Fidelize | O6: Página: 01/01
A7: Product Owner | B7: Garantir que o produto final atenda às necessidades do negócio. Entrega funcional e validada do sistema dentro do escopo. Alinhar entregas com os objetivos estratégicos da empresa/plataforma. | C7: Alto poder sobre decisões de escopo e determina a direção e as prioridades. | D7: Definir a visão do produto, priorizar recursos, tomar decisões estratégicas.
A8: Desenvolvedores | B8: Construir o sistema com qualidade técnica e dentro do prazo. Implementar os módulos com eficiência e segurança. Entregar um sistema funcional, escalável e bem documentado. | C8: Poder técnico elevado na implementação do sistema. | D8: Escrever código, realizar testes, resolver problemas técnicos. | G8: Ref | H8: Atividade | I8: Assunto/Conteúdo | J8: Tipo | K8: Emissor –responsavel | L8: Local | M8: Receptor | N8: Data ou Freqüência | P8: Feedback | S8: Data Feedback | X8: Obs
A9: Time Comercial | B9: Obter dados estratégicos para apoiar vendas e relacionamento. Usar o dashboard para análise de resultados de campanhas. Melhorar performance de vendas e retenção. | C9: Influência média em requisitos voltados a vendas. | D9: Negociar parcerias, fechar vendas, atingir metas de receita. | G9: STK-001 | H9: Kick-off Meeting | I9: Apresentação do projeto, objetivos, escopo, papéis e coleta de feedback inicial dos stakeholders. | J9: Reunião | K9: Gerente de Projeto | L9: Sala de Conferências A | M9: Todas as partes interessadas | N9: 02/08/2025 (início do projeto) | P9: Coleta de feedback inicial sobre expectativas e cronograma | S9: 45885 | X9: Discussões adicionais previstas para o final da primeira sprint.
A10: Marketing | B10: Planejar campanhas mais eficientes com base em dados. Aumentar engajamento com base nos insights e alertas inteligentes da plataforma. | C10: Influência moderada com foco em engajamento. | D10: Planejar campanhas, criar conteúdo, monitorar métricas de marketing. | G10: STK-002 | H10: Reunião de Planejamento | I10: Priorização de funcionalidades, definição de backlog e critérios de aceitação. | J10: Reunião | K10: Scrum Master | L10: Sala de Reuniões Core | M10: Product Owner e equipe de desenvolvimento | N10: 05/08/2025 e a cada 2 semanas | P10: Feedback do Product Owner sobre o backlog e estimativas | S10: Após cada reunião | X10: Planejamento iterativo e acompanhamento de progresso.
A11: UX (User Experience) | B11: Garantir que o sistema seja intuitivo e responsivo. Reduzir fricções na jornada do usuário. Oferecer uma boa experiência para retenção e satisfação. | C11: Poder sobre decisões de usabilidade. | D11: Design de interface, teste de usabilidade, feedback de design. | G11: STK-003 | H11: Reuniões Diárias | I11: Atualização de progresso, identificação de impedimentos e definição de tarefas diárias. | J11: Reunião | K11: Responsável: Scrum Master | L11: Meeting online | M11: Desenvolvedores | N11: Diariamente | P11: Feedback rápido sobre avanços e bloqueios | S11: Durante as reuniões diárias | X11: Comunicação ágil e contínua.
A12: Equipe de Suporte ao Cliente | B12: Ajudar clientes a utilizarem o dashboard corretamente. Reduzir número de chamados e dúvidas. Garantir que os usuários entendam as funcionalidades. | C12: Influência baixa, mas relevante para melhorias contínuas. | D12: Responder a perguntas, resolver problemas, coletar feedback do cliente. | G12: STK-004 | H12: Reunião de Acompanhamento Comercial | I12: Alinhamento do dashboard com as demandas de vendas e clientes B2B. | J12: Reunião | K12: Responsável: Gerente Comercial | L12: Meeting online | M12: Membros da equipe comercial | N12: Quinzenal | P12: Feedback sobre uso dos indicadores e insights | S12: Após cada reunião | X12: Ajustes no dashboard conforme necessidades do time de vendas.
A13: Gerência Executiva/Alta Administração | B13: Avaliar resultados estratégicos e ROI da plataforma. Acompanhar KPIs-chave e justificar investimentos. Ter visão consolidada e estratégica da operação. | C13: Alto poder de decisão estratégica e orçamentária. | D13: Estabelecer metas estratégicas, alocar recursos, tomar decisões de alto nível. | G13: STK-005 | H13: Reunião de Estratégia de Marketing | I13: Planejamento de campanhas baseadas em dados e análise de desempenho via dashboard. | J13: Reunião | K13: Gerente de Marketing | L13: Meeting online | M13: Membros da equipe de marketing | N13: 15/08/2025 e a cada 15 dias | P13: Feedback sobre eficácia das campanhas e relatórios | S13: Após cada reunião | X13: Ajuste de campanhas com base nos insights do dashboard.
G14: STK-006 | H14: Sessões de UX e Design | I14: Testes de usabilidade, prototipagem e análise de interface. | J14: Workshop | K14: Responsável: Líder de UX | L14: Laboratório de Usabilidade | M14: Equipe de UX e Product Owner | N14: Semanalmente | P14: Feedback sobre navegação e experiência do usuário | S14: Após cada sessão | X14: Melhorias contínuas de design e fluxo.
G15: STK-007 | H15: Reunião de Feedback dos Usuários Piloto | I15: Coleta de percepções sobre a primeira versão funcional do dashboard. | J15: Reunião | K15: Responsável: Gerente de Suporte ao Cliente | L15: Meeting online | M15: Usuários piloto e suporte | N15: 10/09/2025 e a cada 2 semanas | P15: Feedback dos usuários sobre usabilidade e performance | S15: Após cada reunião | X15: Resolução de bugs e ajustes rápidos.
G16: STK-008 | H16: Revisão da Sprint e Retrospectiva | I16: Avaliação dos resultados e desempenho da equipe. | J16: Reunião | K16: Scrum Master | L16: Sala de Reuniões Core | M16: Product Owner e equipe de desenvolvimento | N16: A cada sprint (quinzenal) | P16: Feedback sobre entregas e melhorias de processo | S16: Após cada reunião | X16: Ações corretivas e preventivas para o próximo ciclo.
G17: STK-009 | H17: Reunião de Revisão Estratégica | I17: Avaliação do alinhamento do projeto aos objetivos organizacionais e ROI. | J17: Reunião | K17: Responsável: CEO | L17: Sala de Diretoria | M17: Alta Administração | N17: Mensal (última sexta de cada mês) | P17: Feedback sobre indicadores estratégicos | S17: Após cada reunião | X17: Decisões estratégicas sobre o andamento do projeto.
G18: STK-010 | H18: Encerramento do Projeto | I18: Apresentação dos resultados, lições aprendidas e indicadores de sucesso. | J18: Reunião | K18: Gerente de Projeto | L18: Quarto Piso, Bloco B | M18: Todos os stakeholders | N18: 10/11/2025 (fim do projeto) | P18: Feedback geral sobre entregas e satisfação dos stakeholders | S18: 45985 | X18: Entrega do relatório final e encerramento formal do projeto.
H19: Gerente do projeto: Marcella Santana | J19: Elaborado por: Time Fidelize | N19: Aprovado por: Cannoli & FECAP
G20: Alternativas para o campo Tipo de Mensagem: Relatório executivo, Relatório operacional, Cartilha, Apostila, Prontuário de registros. Arquivo, e-Mail, Correio convencional, Carta registrada, Corrier, Telefone (voice-mail), Fax, Reunião, Apresentação, Workshop, Memorando (de/para), Jornal, Vídeo (filme VHS, AVI, etc), Quadro de avisos, Painel, Lista de discução, Internet ou Intranet, entre outras.

Sheet Planejamento de RH

Sheet Organograma da Equipe

Sheet Mapa Competência - Equipe
B8: Perfil de Qualificação | G8: MAPA DE COMPETÊNCIAS
B9: 0 | C9: Nenhum conhecimento | J9: FIDELIZE
B10: 2 | C10: Participou de treinamento | G10: Revisado em Nov/2025
B11: 5 | C11: Domínio básico | G11: Dashboard Cannoli
B12: 8 | C12: Experiência prática | G12: Responsável: Marcella Santana Gonçalves Diniz Rocha
B13: 10 | C13: Especialista | G13: Habilitação
F14: Pessoa | G14: Definição e Priorização de Backlog | H14: Feedback dos usuários e stakeholders | I14: Planejar atividades | J14: Elaborar proposta comercial | K14: Projetar a interface do usuário | L14: Integrar sistemas de terceiros e APIs | M14: Utiliza Planilha | N14: Utiliza VSCODE | O14: Plano de Gerenciamento de RH | P14: Planejamento Estratégico | Q14: Elaborar a W.B.S | R14: Gerencia Projetos | S14: Controle de Qualidade | T14: Criar wireframes | U14: Mitigar riscos | V14: Procedimentos Administrativos | W14: Faturamento da Startup | X14: (…)
D15: Marcella | G15: 8 | H15: 8 | I15: 10 | J15: 5 | K15: 5 | L15: 2 | M15: 10 | N15: 5 | O15: 10 | P15: 5 | Q15: 10 | R15: 10 | S15: 8 | T15: 5 | U15: 8 | V15: 8 | W15: 5
D16: João Pedro | G16: 8 | H16: 5 | I16: 8 | J16: 8 | K16: 8 | L16: 10 | M16: 8 | N16: 10 | O16: 5 | P16: 8 | Q16: 5 | R16: 5 | S16: 10 | T16: 8 | U16: 8 | V16: 5 | W16: 8
D17: Thays Helyda | G17: 8 | H17: 8 | I17: 8 | J17: 8 | K17: 5 | L17: 5 | M17: 10 | N17: 8 | O17: 8 | P17: 10 | Q17: 8 | R17: 8 | S17: 8 | T17: 5 | U17: 8 | V17: 8 | W17: 10
D18: Gustavo de Souza | G18: 2 | H18: 2 | I18: 2 | J18: 0 | K18: 8 | L18: 2 | M18: 5 | N18: 2 | O18: 2 | P18: 5 | Q18: 2 | R18: 2 | S18: 5 | T18: 8 | U18: 5 | V18: 5 | W18: 0
B23: Modelo de registro de treinamento no local de trabalho.

Sheet Mapa de Responsabilidade
B2: Matriz de Responsabilidade
D4: Equipe do Projeto
B5: Ref | C5: Etapas – Atividades | D5: GP | E5: DEV | F5: AD | G5: DS
B6: 1 | C6: Planejamento do Projeto | D6: R / A | E6: C | F6: C | G6: I
B7: 1.1 | C7: Elaboração da WBS | D7: R / A | E7: C | F7: C | G7: I
B8: 1.2 | C8: Definição do Cronograma | D8: R / A | E8: C | F8: C | G8: I
B9: 1.3 | C9: Organização do Repositório (GitHub) | D9: R / A | E9: C | F9: I | G9: I
B10: 1.4 | C10: Desenvolvimento do Sistema | D10: I | E10: R/A | F10: C | G10: C
B11: 1.5 | C11: Implementação do Dashboard | D11: C | E11: R/A | F11: C | G11: I
B12: 1.6 | C12: Análise de Dados e Indicadores | D12: I | E12: C | F12: R/A | G12: I
B13: 1.7 | C13: Planejamento Estratégico do Projeto | D13: R / A | E13: C | F13: C | G13: I
B14: 1.8 | C14: Produção de Relatórios e Documentação | D14: R / A | E14: C | F14: C | G14: I
B15: 1.9 | C15: Entregas de Cibersegurança | D15: R / A | E15: C | F15: I | G15: C
B16: 1.10 | C16: Design e Prototipagem no Figma | D16: I | E16: C | F16: I | G16: R/A
B17: 1.11 | C17: Controle de Qualidade do Sistema | D17: R / A | E17: C | F17: C | G17: C
B18: 1.12 | C18: Mitigação de Riscos | D18: R / A | E18: C | F18: C | G18: I
B19: 1.13 | C19: Feedback de Stakeholders e Usuários | D19: R / A | E19: C | F19: C | G19: I
B20: 1.14 | C20: Comunicação e Reuniões de Acompanhamento | D20: R / A | E20: C | F20: C | G20: I | L20: EQUIPE DO PROJETO
B21: 1.15 | C21: Avaliação de Desempenho da Equipe | D21: R / A | E21: C | F21: C | G21: I | L21: Marcella Santana | M21: Gerente de Projeto
B22: 1.16 | C22: Integração de APIs e Funcionalidades | D22: I | E22: R/A | F22: C | G22: I | L22: João Pedro Brosselin | M22: Desenvolvedor Full Stack / Líder Técnico
B23: 1.17 | C23: Supervisão do Dashboard | D23: I | E23: C | F23: R/A | G23: I | L23: Thays Helyda da Silva | M23: Analista de Dados / Empreendedorismo
B24: 1.18 | C24: Planejamento de IA e Machine Learning | D24: R / A | E24: R | F24: C | G24: I | L24: Gustavo de Souza | M24: Colaborador de Suporte / Design
B25: 1.19 | C25: Fechamento e Relatório Final | D25: R / A | E25: C | F25: C | G25: I
B26: 1.20 | C26: Identificação de problemas de qualidade e participação na busca de soluções | D26: R / A | E26: C | F26: C | G26: R
B27: 1.21 | C27: Implementação de ações corretivas e preventivas | D27: R / A | E27: C | F27: C | G27: R
B28: 1.22 | C28: Promoção de uma cultura de melhoria contínua da qualidade na empresa | D28: R / A | E28: C | F28: C | G28: R
B29: 1.23 | C29: Garantia de conformidade com requisitos regulatórios | D29: R / A | E29: C | F29: C | G29: R | L29: Legenda - - Gráfico RACI (Responsabilidade, Aprovação, Consultado e Informado)
B30: 1.24 | C30: Plano de Gerenciamento de RH | D30: R / A | E30: R | F30: C | G30: C
B31: 1.25 | C31: Elaborar o Planejamento Estratégico | D31: R / A | E31: R | F31: C | G31: C | L31: R - Responsável pela Execução
B32: 1.26 | C32: Elaborar o Cronograma de Atividades | D32: R / A | E32: R | F32: C | G32: C | L32: A - Aprovação
B33: 1.27 | C33: Treinamento de Desenvolvimento da Equipe | D33: R / A | E33: R | F33: C | G33: C | L33: C - Consultado
B34: 1.28 | C34: Avaliação de desempenho e gestão de feedback | D34: R / A | E34: R | F34: C | G34: C | L34: I - Informado
B35: 1.29 | C35: Tomada de decisões financeiras estratégicas | D35: R / A | E35: R | F35: C | G35: C | L35: P - Participante
B36: 1.30 | C36: Desenvolvimento de metas e objetivos organizacionais | D36: R / A | E36: R | F36: C | G36: C
B37: 1.31 | C37: Monitoramento do progresso em direção às metas estratégicas | D37: R / A | E37: R | F37: C | G37: C
B38: 1.32 | C38: Resolução de conflitos e promoção de um ambiente de trabalho saudável | D38: R / A | E38: R | F38: C | G38: C
B39: 1.33 | C39: Aquisição de materiais e suprimentos necessários para as operações da empresa | D39: R / A | E39: R | F39: C | G39: C
B40: 1.34 | C40: Garantia de conformidade com requisitos regulatórios | D40: R / A | E40: R | F40: C | G40: C
B41: 1.35 | C41: Preparação de relatórios gerenciais para a alta administração | D41: R / A | E41: R | F41: C | G41: C
B42: 1.36 | C42: Tomada de decisões com base em informações quantitativas e qualitativas | D42: R / A | E42: R | F42: C | G42: C
B43: 1.37 | C43: Desenvolvimento de Estratégias de Vendas | D43: R / A | E43: C | F43: R | G43: C
B44: 1.38 | C44: Definição de metas de vendas e objetivos a curto e longo prazo | D44: R / A | E44: C | F44: R | G44: C
B45: 1.39 | C45: Análise de métricas de vendas, como conversão, ticket médio e taxa de fechamento | D45: R / A | E45: C | F45: R | G45: C
B46: 1.40 | C46: Treinamento de Desenvolvimento da Equipe Comercial | D46: R / A | E46: C | F46: R | G46: C
B47: 1.41 | C47: Avaliação de desempenho e gestão de finanças | D47: R / A | E47: C | F47: R | G47: C
... B90: 1.84 | C90: Ter uma visão clara do aplicativo e seu posicionamento no mercado | D90: R / A | E90: C | F90: C | G90: C

Sheet Gráfico de Gantt
E3: Saúde e bem-estar na palma da sua mão
A5: Insira o nome do Líder do projeto na célula B3. Insira a data de Início do projeto na célula E3. Início do projeto: o rótulo está na célula C3. | D5: Líder do projeto: Gerente de Projeto | E5: Início do projeto: | G5: 45160
A6: A semana de exibição na célula E4 representa a semana inicial a ser exibida no cronograma do projeto na célula I4. A data de início do projeto é considerada Semana 1. Para alterar a semana de exibição, basta inserir um novo número da semana na célula E4. A data inicial para cada semana, começando com a semana de exibição na célula E4, começa na célula I4 e é calculada automaticamente. Há 8 semanas representadas nesse modo de exibição que vão da célula I4 a célula BF4. Você não deve modificar essas células. Semana de exibição: o rótulo está na célula C4. | E6: Semana de exibição: | G6: 1 | K6: =K7 -> 45159 | R6: =R7 -> 45166 | Y6: =Y7 -> 45173 | AF6: =AF7 -> 45180 | AM6: =AM7 -> 45187 | AT6: =AT7 -> 45194 | BA6: =BA7 -> 45201 | BH6: =BH7 -> 45208
A7: As células I5 a BL5 contêm o número de dias da semana representado no bloco de células acima de cada célula de data e são calculadas automaticamente. Você não deve modificar essas células. A data de hoje é contornada em vermelho (hex #AD3815) a partir da data de hoje na linha 5, passando pela coluna de data inteira até o final do cronograma do projeto. | K7: =Início_do_projeto-WEEKDAY(Início_do_projeto,1)+2+7*(Semana_de_exibição-1) -> 45159 | L7: =K7+1 -> 45160 | M7: =L7+1 -> 45161 | N7: =M7+1 -> 45162 | O7: =N7+1 -> 45163 | P7: =O7+1 -> 45164 | Q7: =P7+1 -> 45165 | R7: =Q7+1 -> 45166 | S7: =R7+1 -> 45167 | ... BN7: =BM7+1 -> 45214
A8: Esta linha inclui cabeçalhos do cronograma do projeto que estão abaixo deles. Navegue de B6 a BL6 para ouvir o conteúdo. A primeira letra de cada dia da semana da data acima daquele cabeçalho começa na célula I6 e continua até a célula BL6. Todo o gráfico de linha do tempo de projeto é gerado automaticamente com base nas datas de início e término inseridas, usando os formatos condicionais. Não modifique o conteúdo nas células dentro das colunas após a coluna I, começando na célula I7. | D8: TAREFA | E8: ATRIBUÍDO PARA | F8: PROGRESSO | G8: INÍCIO | H8: TÉRMINO | J8: DIAS | K8: =LEFT(TEXT(K7,"ddd"),1) -> s | L8: =LEFT(TEXT(L7,"ddd"),1) -> t | M8: =LEFT(TEXT(M7,"ddd"),1) -> q | N8: =LEFT(TEXT(N7,"ddd"),1) -> q | O8: =LEFT(TEXT(O7,"ddd"),1) -> s | P8: =LEFT(TEXT(P7,"ddd"),1) -> s | Q8: =LEFT(TEXT(Q7,"ddd"),1) -> d | R8: =LEFT(TEXT(R7,"ddd"),1) -> s | ... BN8: =LEFT(TEXT(BN7,"ddd"),1) -> d
A9: Não exclua esta linha. Esta linha ficará oculta para preservar uma fórmula usada para realçar o dia atual no cronograma do projeto. | J9: =IF(OR(ISBLANK(início_da_tarefa),ISBLANK(término_da_tarefa)),"",término_da_tarefa-início_da_tarefa+1) -> 4
A10: A célula B8 contém o título do exemplo da Fase 1. Insira um novo Título na célula B8. Na célula C8, insira o nome a atribuir à fase, caso ela se aplique ao seu projeto. Na célula D8, insira o Progresso para a fase inteira, caso ela se aplique ao seu projeto. Nas células E8 e F8, insira as datas de início e término para a fase inteira, caso ela se aplique ao seu projeto. O gráfico de Gantt preenche automaticamente as datas apropriadas e sombreia de acordo com o andamento inserido. Para excluir a fase e trabalhar apenas nas tarefas, basta excluir essa linha. | D10: Iniciação | J10: =IF(OR(ISBLANK(início_da_tarefa),ISBLANK(término_da_tarefa)),"",término_da_tarefa-início_da_tarefa+1) -> 3
A11: A célula B9 contém a tarefa de exemplo "Tarefa 1". Insira um novo nome da tarefa na célula B9. Insira uma pessoa para atribuir a tarefa na célula C9. Insira o andamento da tarefa na célula D9. Uma barra de progresso é exibida na célula e fica sombreada de acordo com o número na célula. Por exemplo, 50% de progresso sombreia metade da célula. Insira a data de início da tarefa na célula E9. Insira a data de término da tarefa na célula F9. Uma barra de status sombreada das datas inseridas aparece em blocos começando na célula I9 até BL9. | D11: Definir os objetivos do aplicativo e sua proposta de valor | G11: =Início_do_projeto -> 45160 | H11: =G11+3 -> 45163 | J11: =IF(OR(ISBLANK(início_da_tarefa),ISBLANK(término_da_tarefa)),"",término_da_tarefa-início_da_tarefa+1) -> 5
A12: As linhas 10 a 13 repetem o padrão da linha 9. Repita as instruções da célula A9 para todas as linhas de tarefas nesta planilha. Substitua os dados de exemplo. Um exemplo de outra fase começa na célula A14. Continue inserindo tarefas nas células A10 a A13 ou vá para a célula A14 para saber mais. | D12: Tarefa 2 | J12: =IF(OR(ISBLANK(início_da_tarefa),ISBLANK(término_da_tarefa)),"",término_da_tarefa-início_da_tarefa+1) -> 6
D13: Tarefa 3 | J13: =IF(OR(ISBLANK(início_da_tarefa),ISBLANK(término_da_tarefa)),"",término_da_tarefa-início_da_tarefa+1) -> 3
D14: Tarefa 4 | J14: =IF(OR(ISBLANK(início_da_tarefa),ISBLANK(término_da_tarefa)),"",término_da_tarefa-início_da_tarefa+1)
D15: Tarefa 5 | J15: =IF(OR(ISBLANK(início_da_tarefa),ISBLANK(término_da_tarefa)),"",término_da_tarefa-início_da_tarefa+1) -> 5
A16: A célula à direita contém o título do exemplo da Fase 2. Você pode criar uma nova fase a qualquer momento na coluna B. Este cronograma de projeto não exige fases. Para remover a fase, basta excluir a linha. Para criar um novo bloco de fases nesta linha, digite um novo Título na célula à direita. Para continuar a adicionar tarefas à fase acima, insira uma nova linha acima desta e preencha os dados da tarefa como na instrução da célula A9. Atualize os detalhes da Fase na célula à direita, com base nas instruções da célula A8. Continue navegando para baixo nas células da coluna A para saber mais. Se você ainda não adicionou as novas linhas nesta planilha, encontrará 2 exemplos adicionais de blocos de fase que foram criados nas células B20 e B26. Caso contrário, navegue pelas células da coluna A para localizar os blocos adicionais. Repita as instruções das células A8 e A9 sempre que precisar. | D16: Título Fase 2 | J16: =IF(OR(ISBLANK(início_da_tarefa),ISBLANK(término_da_tarefa)),"",término_da_tarefa-início_da_tarefa+1) -> 6
D17: Tarefa 1 | J17: =IF(OR(ISBLANK(início_da_tarefa),ISBLANK(término_da_tarefa)),"",término_da_tarefa-início_da_tarefa+1) -> 4
D18: Tarefa 2 | J18: =IF(OR(ISBLANK(início_da_tarefa),ISBLANK(término_da_tarefa)),"",término_da_tarefa-início_da_tarefa+1) -> 3
D19: Tarefa 3 | J19: =IF(OR(ISBLANK(início_da_tarefa),ISBLANK(término_da_tarefa)),"",término_da_tarefa-início_da_tarefa+1) -> 4
D20: Tarefa 4 | J20: =IF(OR(ISBLANK(início_da_tarefa),ISBLANK(término_da_tarefa)),"",término_da_tarefa-início_da_tarefa+1)
D21: Tarefa 5 | J21: =IF(OR(ISBLANK(início_da_tarefa),ISBLANK(término_da_tarefa)),"",término_da_tarefa-início_da_tarefa+1) -> 6
A22: Bloco de título de fase de exemplo | D22: Título Fase 3 | J22: =IF(OR(ISBLANK(início_da_tarefa),ISBLANK(término_da_tarefa)),"",término_da_tarefa-início_da_tarefa+1) -> 5
D23: Tarefa 1 | J23: =IF(OR(ISBLANK(início_da_tarefa),ISBLANK(término_da_tarefa)),"",término_da_tarefa-início_da_tarefa+1) -> 6
D24: Tarefa 2 | J24: =IF(OR(ISBLANK(início_da_tarefa),ISBLANK(término_da_tarefa)),"",término_da_tarefa-início_da_tarefa+1) -> 5
D25: Tarefa 3 | J25: =IF(OR(ISBLANK(início_da_tarefa),ISBLANK(término_da_tarefa)),"",término_da_tarefa-início_da_tarefa+1) -> 5
D26: Tarefa 4 | J26: =IF(OR(ISBLANK(início_da_tarefa),ISBLANK(término_da_tarefa)),"",término_da_tarefa-início_da_tarefa+1)
D27: Tarefa 5 | J27: =IF(OR(ISBLANK(início_da_tarefa),ISBLANK(término_da_tarefa)),"",término_da_tarefa-início_da_tarefa+1) -> #VALUE!
A28: Bloco de título de fase de exemplo | D28: Título Fase 4 | J28: =IF(OR(ISBLANK(início_da_tarefa),ISBLANK(término_da_tarefa)),"",término_da_tarefa-início_da_tarefa+1) -> #VALUE!
D29: Tarefa 1 | G29: data | H29: data | J29: =IF(OR(ISBLANK(início_da_tarefa),ISBLANK(término_da_tarefa)),"",término_da_tarefa-início_da_tarefa+1) -> #VALUE!
D30: Tarefa 2 | G30: data | H30: data | J30: =IF(OR(ISBLANK(início_da_tarefa),ISBLANK(término_da_tarefa)),"",término_da_tarefa-início_da_tarefa+1) -> #VALUE!
D31: Tarefa 3 | G31: data | H31: data | J31: =IF(OR(ISBLANK(início_da_tarefa),ISBLANK(término_da_tarefa)),"",término_da_tarefa-início_da_tarefa+1) -> #VALUE!
D32: Tarefa 4 | G32: data | H32: data | J32: =IF(OR(ISBLANK(início_da_tarefa),ISBLANK(término_da_tarefa)),"",término_da_tarefa-início_da_tarefa+1)
D33: Tarefa 5 | G33: data | H33: data | J33: =IF(OR(ISBLANK(início_da_tarefa),ISBLANK(término_da_tarefa)),"",término_da_tarefa-início_da_tarefa+1)
A34: Esta é uma linha vazia | J34: =IF(OR(ISBLANK(início_da_tarefa),ISBLANK(término_da_tarefa)),"",término_da_tarefa-início_da_tarefa+1)
A35: Esta linha marca o final do Cronograma do projeto. NÃO insira nada nessa linha. Insira novas linhas ACIMA desta linha para continuar a construção do cronograma de projeto. | D35: Insira novas linhas ACIMA desta | J35: =IF(OR(ISBLANK(início_da_tarefa),ISBLANK(término_da_tarefa)),"",término_da_tarefa-início_da_tarefa+1)

Sheet PV_dependência
A3: Soma de Custos
A4: Dependência | B4: Responsável | C4: Etapas – Atividades - | D4: Ref | E4: Total
A5: 1.1 | B5: GERENTE DE PROJETO | C5: Definir os objetivos do aplicativo e sua proposta de valor | D5: 1.1 | E5: 1000
C6: Formar uma equipe de desenvolvimento e design | D6: 1.3 | E6: 1000
C7: Identificar as principais funcionalidades e recursos a serem incluídos | D7: 1.2 | E7: 2000
A8: 1.3 | B8: DESIGN | C8: Realizar o design da interface do usuário (UI) | D8: 3.1 | E8: 2000
B9: GERENTE DE PROJETO | C9: Definir os requisitos detalhados do aplicativo (escopo) | D9: 2.2 | E9: 700
B10: (vazio) | C10: Planejamento | D10: 2
A11: 10.1.1 | B11: DESEMPENHO | C11: Realizar análises regulares sobre o desempenho do aplicativo | D11: 10.1.1 | E11: 4000
A12: 10.1.2 | B12: COMERCIAL | C12: Explorar parcerias com empresas relacionadas à saúde e bem-estar | D12: 10.1.2 | E12: 1000
A13: 10.1.3 | B13: COMERCIAL | C13: Avaliar a possibilidade de oferecer versões premium ou modelos de assinatura | D13: 10.1.3 | E13: 1000
A14: 2.1 | B14: GERENTE DE PROJETO | C14: Realizar uma análise de mercado para entender concorrentes e demandas | D14: 2.1 | E14: 2000
A15: 2.2 | B15: GERENTE DE PROJETO | C15: Criar um cronograma detalhado com marcos e prazos | D15: 2.3 | E15: 400
C16: Dicas de saúde e bem-estar | D16: 2.2.1 | E16: 500
C17: Integração com sistemas de monitoramento de saúde | D17: 2.2.4 | E17: 200
C18: Mapas com locais de academias e parques | D18: 2.2.3 | E18: 800
C19: Planos de exercícios físicos personalizados | D19: 2.2.2 | E19: 1000
A20: 2.3 | B20: (vazio) | C20: Design e Prototipagem | D20: 3
A21: 3.1 | B21: DESIGN | C21: Navegação simples entre as funcionalidades | D21: 3.1.1 | E21: 500
A22: 3.1.1 | B22: DESIGN | C22: Criar protótipos interativos para validar o fluxo de usuário | D22: 3.1.2 | E22: 500
A23: 3.1.2 | B23: DESIGN | C23: Experiência do usuário (UX) | D23: 3.2 | E23: 1000
A24: 3.2 | B24: DESIGN | C24: Interface limpa e intuitiva | D24: 3.2.1 | E24: 500
A25: 3.2.1 | B25: (vazio) | C25: Desenvolvimento | D25: 4
A26: 3.2.2 | B26: DESIGN | C26: Teste de UI / UX | D26: 3.2.2 | E26: 700
A27: 4.1 | B27: DESENVOLVIMENTO | C27: Desenvolver a estrutura do aplicativo | D27: 4.1 | E27: 500
A28: 4.1.2 | B28: DESENVOLVIMENTO | C28: Front-end: Interface do usuário e interações | D28: 4.1.2 | E28: 5000
A29: 4.2 | B29: DESENVOLVIMENTO | C29: Implementar as funcionalidades principais | D29: 4.2 | E29: 700
A30: 4.2.1 | B30: DESENVOLVIMENTO | C30: Módulo de dicas de saúde | D30: 4.2.1 | E30: 500
A31: 4.2.2 | B31: DESENVOLVIMENTO | C31: Gerador de planos de exercícios | D31: 4.2.2 | E31: 300
A32: 4.2.3 | B32: DESENVOLVIMENTO | C32: Integração com APIs de mapas para localização de academias e parques | D32: 4.2.3 | E32: 1000
A33: 5.1 | B33: SEGURANÇA | C33: Integrar o aplicativo com sistemas de monitoramento de saúde, como dispositivos wearable ou aplicativos de rastreamento | D33: 5.1 | E33: 3000
A34: 5.2 | B34: SEGURANÇA | C34: Garantir a segurança e privacidade dos dados do usuário | D34: 5.2 | E34: 1000
A35: 5.3 | B35: SEGURANÇA | C35: Testar a integração para assegurar que os dados são sincronizados corretamente | D35: 5.3 | E35: 1000
A36: 6.1 | B36: QUALIDADE | C36: Realizar testes de qualidade e desempenho em diversas plataformas (iOS, Android) | D36: 6.1 | E36: 30000
A37: 6.1.2 | B37: UX | C37: Testar a usabilidade do aplicativo com usuários reais | D37: 6.1.2 | E37: 700
... A47: 9.1.3 | B47: EQUIPE TÉCNICA | C47: Realizar campanhas de mídia social e anúncios online | D47: 9.1.3 | E47: 10000
A48: (vazio) | B48: (vazio) | C48: Avaliação e Aperfeiçoamento | D48: 10
C49: Iniciação | D49: 1
C50: Integração com sistemas de monitoramento de saúde | D50: 5
C51: Lançamento | D51: 7
C52: Marketing e Divulgação | D52: 9
C53: Pós-lançamento | D53: 8
C54: Testes | D54: 6
A55: Total Geral | E55: 150000

Sheet Cronograma_de_Custos (2)
B2: 5.2. CRONOGRAMA DE CUSTOS
B5: Ref | C5: Etapas – Atividades - Marcos
D6: 1 | E6: 2 | F6: 3 | G6: 4 | H6: 5 | I6: 6 | J6: 7 | K6: 8 | L6: 9 | M6: 10 | N6: 11 | O6: 12 | P6: 13 | Q6: 14 | R6: 15 | S6: 16 | T6: 17 | U6: 18 | V6: 19 | W6: 20 | X6: 21 | Y6: 22 | Z6: 23 | AA6: 24
D7: Agosto | H7: Setembro | L7: Outubro | P7: Novembro | T7: Dezembro | X7: Janeiro
B8: 1.1 | C8: Plano do Projeto | D8: 30000
B9: 1.2 | C9: Controle | H9: 5000 | L9: 5000 | P9: 5000 | T9: 5000
B10: 1.3 | C10: Fechamento | X10: 10000
B11: 2 | C11: Adequar o Espaço Físico | L11: 20000 | P11: 40000 | T11: 10000 | X11: 10000
B12: 3.1 | C12: Equipamentos de Ginástica | H12: 10000 | L12: 25000 | P12: 25000 | T12: 25000 | X12: 5000
B13: 3.2 | C13: Equipamentos de Apoio e Administração | L13: 15000 | P13: 15000 | T13: 20000 | X13: 10000
B14: 4 | C14: Contratar Mão de Obra | X14: 7000
B15: 5.1 | C15: Contratar empresa para informatização da academia | T15: 4000 | X15: 4000
B16: 5.2 | C16: Adquirir Sistemas de Segurança | T16: 2500 | X16: 2500
B17: 5.3 | C17: Fechar Convênio com Estacionamento próximo ao local | X17: 0
B18: 5.4 | C18: Contratação de Designer de Interiores | H18: =20000*35% -> 7000 | L18: =13000/4 -> 3250 | P18: =13000/4 -> 3250 | T18: =13000/4 -> 3250 | X18: =13000/4 -> 3250
